{
  "title": "宜蘭四季節慶生活：跟著在地人過節的深度體驗",
  "slug": "taiwan-entertainment-festivals-yilan-宜蘭四季節慶生活-跟著在地人過節的深度體驗-c38f43",
  "industry": "entertainment",
  "category": "festivals",
  "area": "yilan",
  "url": "https://taiwan-encyclopedia.vercel.app/articles/taiwan-entertainment-festivals-yilan-宜蘭四季節慶生活-跟著在地人過節的深度體驗-c38f43.html",
  "published": "2026-03-27",
  "quality_score": 6.5,
  "word_count": 1724,
  "tags": [
    "宜蘭節慶",
    "四季體驗",
    "在地文化",
    "民俗活動",
    "傳統祭典"
  ],
  "content": "**四季更迭中的宜蘭節慶，才是最真實的蘭陽風情**\n\n如果你只知道宜蘭國際童玩藝術節，那你錯過了宜蘭最迷人的一面。真正的宜蘭節慶魅力，藏在四季更迭的生活節奏裡。春天的農忙慶收、夏夜的廟會熱鬧、秋日的豐收感恩、冬季的溫泉祭典——每一季都有屬於在地人的慶典時光，而這些才是體驗宜蘭靈魂的最佳時機。\n\n## 四季節慶的生活韻味\n\n宜蘭的節慶文化有個特色：它們不是為了觀光而生，而是紮根於農漁業生活的真實需求。春耕秋收的農事節奏、漁汛來去的海洋時令、甚至是東北季風帶來的溫泉季節，都催生出不同的慶祝方式。這種與自然共舞的節慶傳統，讓每次參與都像是加入了一場在地人的生活儀式。\n\n更棒的是，宜蘭人熱情但不刻意，你可以自然地融入他們的慶典中，感受那種「今天就是要好好玩」的單純快樂。無論是廟口的流水席、夜市的遊戲攤，還是海邊的篝火晚會，都能讓你暫時忘記都市生活的複雜，回到最基本的人情味。\n\n## 季節限定體驗推薦\n\n**頭城搶孤節（農曆七月）**\n地址：宜蘭縣頭城鎮和平街\n這是臺灣最刺激的民俗競技，壯漢們徒手爬上13公尺高的孤棚搶奪供品。晚上8點開始的搶孤比賽是最高潮，但下午3點就該到現場卡位。現場的叫好聲、加油聲，加上海風徐徐，那種熱血沸騰的感覺完全不輸演唱會。記得帶個小板凳，因為要站很久，但絕對值得。\n\n**冬山河春節燈會（農曆正月）**\n地址：宜蘭縣五結鄉親水公園\n比起臺北燈節的人山人海，冬山河燈會有種愜意的節奏感。重點不只是看燈，而是那種全家出動、邊走邊聊的悠閒氛圍。晚上6點開燈後，最美的時段是7點到8點半，倒影在水面上的燈光特別夢幻。附近有很多小吃攤，建議先填飽肚子再慢慢逛。\n\n**南澳泰雅豐年祭（7-8月）**\n地址：宜蘭縣南澳鄉各村落\n這是少數開放給非原住民參與的豐年祭，但請記住你是客人的身份。最精彩的是傳統歌舞表演和勇士舞，通常在晚上7點開始。現場會教你簡單的舞步，不要害羞，泰雅族人很喜歡看到外人加入他們的慶典。穿著以舒適為主，記得帶防蚊液。\n\n**礁溪溫泉季（11月-2月）**\n地址：宜蘭縣礁溪鄉各溫泉業者\n這個季節的礁溪有種特別的慵懶氛圍。除了泡湯，重點是那些圍繞溫泉而生的夜間活動：溫泉市集、街頭表演、還有業者聯合舉辦的「溫泉之夜」活動。建議選擇週五晚上參與，當地人下班後的熱鬧程度比假日更有生活感。\n\n**宜蘭餅節（中秋前後）**\n地址：宜蘭市各糕餅店及文化中心\n這是一個很在地的小節慶，主要是糕餅業者聯合推廣的活動，但氣氛意外地溫馨。重點是免費試吃和DIY體驗課程，特別推薦「牛舌餅製作體驗」，2小時課程NT$350，學會後回家可以炫耀很久。現場常有即興的音樂表演，是個很chill的週末活動。\n\n## 實用資訊\n\n**交通方式：**\n從臺北出發，搭乘臺鐵至宜蘭站約1小時，車票NT$218。市區內節慶活動多可步行或搭公車（單趟NT$15-25）到達。建議使用悠遊卡，大部分交通工具都接受。如果要跑多個地點，租機車是最方便的選擇，一天約NT$400-600。\n\n**費用預算：**\n大部分傳統節慶活動免費參觀，但建議準備NT$500-800的現金用於小吃和紀念品。DIY體驗活動費用約NT$200-500不等。住宿費用因季節而異，一般民宿NT$1,500-3,000/晚。\n\n**時間安排：**\n建議停留2天1夜，第一天參與節慶活動，第二天體驗在地生活。大部分節慶活動在週末舉行，平日則可以探索節慶相關的文化景點或工坊。\n\n## 融入在地的小秘訣\n\n參與宜蘭節慶最重要的心態是「放慢腳步」。不要想著拍照打卡，而是真正去感受現場的氛圍。在廟會現場，可以主動跟攤販聊天，他們常常是當地文史的活字典。參與傳統祭典時，記得保持尊重的態度，不要大聲喧嘩或隨意拍攝宗教儀式。\n\n如果想更深度體驗，建議選擇民宿而非飯店，民宿主人通常很樂意分享當地節慶的小道訊息。有些隱藏版的慶典活動，只有在地人才知道確切時間和地點。另外，宜蘭人習慣「呷飽沒」的問候方式，不妨學會這句話，能迅速拉近與在地人的距離。\n\n記住，真正的節慶體驗不在於看到多少活動，而在於你有多深入地參與其中。在宜蘭，每一個節慶都是一扇窗，讓你看見臺灣最純樸的生活情調。",
  "license": "CC BY 4.0"
}