{
  "title": "臺北夜市伴手禮獵人：越夜越有趣的臺式土產尋寶指南",
  "slug": "taiwan-shopping-souvenir-gifts-taipei-臺北夜市伴手禮獵人-越夜越有趣的臺式土產尋寶指南-0b1528",
  "industry": "shopping",
  "category": "souvenir-gifts",
  "area": "taipei",
  "url": "https://taiwan-encyclopedia.vercel.app/articles/taiwan-shopping-souvenir-gifts-taipei-臺北夜市伴手禮獵人-越夜越有趣的臺式土產尋寶指南-0b1528.html",
  "published": "2026-05-22",
  "quality_score": 7.5,
  "word_count": 2291,
  "tags": [
    "台北伴手礼",
    "夜市美食",
    "大稻埕",
    "永乐市场",
    "台北旅游"
  ],
  "content": "提起臺北伴手禮，多數人直覺想到的是鳳梨酥、太陽餅這類放在免稅店顯眼位置的經典款。但如果你想找點不一樣的、更有「臺北味道」的禮物，我建議把購物時間往傍晚之後調——這個城市最有生命力的交易，其實發生在夜市裡。\n\n臺北的夜市文化不只是吃小吃那麼簡單，從永樂市場到饒河街，夜市周邊藏著不少傳承數十年的乾貨舖、餅舖和茶行，這些才是老臺北人送禮的口袋名單。\n\n**從清程式碼頭到霓虹燈下：大稻埕的茶與布料**\n\n大稻埕曾是臺北最熱鬧的港口商城，如今保留了全臺最完整的老屋商業街區。這裡的伴手禮有個獨特之處：很多店家本身就是製作出海口，而非只做觀光客生意。\n\n迪化街上「林華泰茶行」從1879年創業至今超過140年，老闆第五代仍在前店顧攤。這裡的烏龍茶按斤論兩賣，入門款高山茶約 NT$800-1200/600g，比信義區觀光茶行的同級品便宜兩成左右。重點是他們願意讓客人開啟茶罐現聞香氣，這種「先試再買」的自信，是連鎖店給不了的體驗。每年農曆年前是旺季，上門的多是本地婆婆媽媽，不是外地遊客。\n\n霞海城煌廟旁邊的「李日興」主打古早味臺式喜餅與漢餅，老師傅手桿的紅豆核桃餅是招牌，一盒四塊 NT$320-450。他們保留了大量日治時期的糕餅模具，牆上掛著泛黃的結婚照，有些是民國50年代的泛黃相紙。這種「活生生的婚俗博物館」氣質，讓伴手禮不只是食物，更像帶得走的臺北生活記憶。大稻埕走到底就是臺北橋，這裡早年可是船隻卸貨的港口，現在反而是機車呼嘯的都市邊緣——時空交錯的奇幻感，正是 Walking in Taipei 最迷人的地方。\n\n**藏在夜市後巷的生活老舖：饒河街與寧夏夜市周邊**\n\n饒河街夜市正門口的「丸林」滷味是臺北人從小吃到大的老味道，他們的空運滷味真空包裝很適合帶回飯店冰著，晚上逛完夜市回房當消夜。這家店的特殊之處在於：不做觀光團生意，全部是本地老顧客上門，招牌雞腳凍 NT$120/盒，滷牛腱 NT$380/斤，價格比松山機場免稅店實惠許多。\n\n離饒河街步行十分鐘的「王記府城口味」是少數在臺北賣南部碗粿的老攤，老闆娘是臺南人，每天手工製作的草仔粿 NT$15/顆，黑糖紅豆、花生芝麻兩種口味。他們沒有店面，就在一棟老公寓的一樓騎樓擺張桌子，下午三點後才開始營業。這種「schedule式的隱藏版」，反而成了IG上瘋傳的另類打卡點。我個人偏好他們的花生芝麻，甜度剛好不會膩，配杯無糖茶剛好中和。\n\n寧夏夜市靠近建成公園那一側的「打鐵豆」專賣手工花生糖，老闆堅持用本土花生而非進口貨。一包 NT$180起，口味選擇不多但品質穩定。這種「少量產」的模式有個好處：每次買到都是新鮮製作的，不是那種在架子上擺半年的工業製品。\n\n**一個容易被忽略的冷知識**\n\n很多人以為要「去九份」才能買到芋頭類產品，但事實上，九份老街上八成的芋頭製品其實是從臺北中央工廠批發過去的「遊客專線產品」，真正的手工芋圓反而在大稻埕的乾貨雜糧店或傳統市場裡。慈聖宮前的傳統市場內有幾家阿婆手工製作的芋粿巧，一份 NT$50-80，這才是真正「產地直銷」的質感。\n\n**永樂市場裡的職業級採購路線**\n\n如果時間夠，建議下午四點後去永樂市場——這時批發商大多已離開，散客可以慢慢挑。這裡聚集了全臺南北乾貨批發商，\n「林記韓式泡菜」的韓式泡菜口感與首爾當地相當接近，\n一罐 NT$150-200，\n真空包裝後可直接帶上飛機。\n\n永樂市場後棟二樓的「三記」南北貨三十年曆史，老闆對各類乾貨的產地與等級瞭若指掌，買之前先問老闆建議，往往能得到意想不到的知識。\n像是：鮑魚乾不只是「大小」差別那麼簡單，澳洲產和日本產的口感差距明顯，\n送給懂得吃的人，一公斤日本產幹鮑的價格約 NT$16,000-20,000，絕對是大禮。\n\n**實用資訊**\n\n| 店鋪 | 位置 | 特色 | 價格帶 |\n|------|------|------|--------|\n| 林華泰茶行 | 大稻埕迪化街 | 百年老茶行，烏龍茶現賣 | NT$800-1200/600g |\n| 李日興 | 大稻埕霞海城隍廟旁 | 古早味漢餅、喜餅 | NT$320-450/盒 |\n| 丸林滷味 | 饒河街夜市 | 真空氣炸花生、雞腳凍 | NT$120-380 |\n| 王記府城口味 | 松山車站附近騎樓 | 臺南Style草仔粿 | NT$15/顆 |\n| 打鐵豆 | 寧夏夜市旁 | 手作花生糖 | NT$180-250 |\n| 三記南北貨 | 永樂市場2樓 | 乾貝、鮑魚等高階乾貨 | 時價 |\n\n**交通與營業時間**\n\n多數店鋪採「看天吃飯」營業模式，大稻埕店家多在上午十點後開門，晚間七點打烊；饒河街與寧夏夜市相關店鋪則恰恰相反——下午三點後才開始營業，深夜十一點還能敲門買東西。建議安排下午的大稻埕行程，加上傍晚過後的夜市採購，形成一個「從古老城市吃到現代夜市」的完整 Loop。\n\n捷運可達性極佳：\n- 大稻埕：捷運大橋頭站1號出口步行3分鐘\n- 饒河街夜市：捷運松山站2號出口直達\n- 寧夏夜市：捷運中山站或雙連站步行8分鐘\n\n**一個小提醒**\n\n買散裝食品時，很多店家會主動提供紙盒+塑膠袋的傳統包裝，但如果你想降低環境負擔，建議自備購物袋前往——臺北很多老店其實很樂意顧客自己帶容器來裝。另外，週末下午的大稻埕人潮洶湧，想要安靜跟老闆聊聊天談採購，最好選平日上午造訪。\n\n這些夜市周邊的隱藏版店家，最大的價值不在於「低價」，而在於——它們還在認真做一件小事，把一件事做好、做一輩子。這種精神本身，就是最臺北的土產。",
  "license": "CC BY 4.0"
}