{
  "title": "臺中文化聚落深度遊：5個遠離人潮的在地文化體驗",
  "slug": "taiwan-tourism-cultural-villages-taichung-臺中文化聚落深度遊-5個遠離人潮的在地文化體驗-784a98",
  "industry": "tourism",
  "category": "cultural-villages",
  "area": "taichung",
  "url": "https://taiwan-encyclopedia.vercel.app/articles/taiwan-tourism-cultural-villages-taichung-臺中文化聚落深度遊-5個遠離人潮的在地文化體驗-784a98.html",
  "published": "2026-07-12",
  "quality_score": 6.5,
  "word_count": 1103,
  "tags": [
    "台中文化聚落",
    "台中眷村",
    "台中文創",
    "清水眷村",
    "梧棲文化出張所"
  ],
  "content": "說到臺中的文化聚落，很多人只想到彩虹眷村或審計新村，但臺中的魅力遠不止這些已被觀光化的景點。這座城市有種獨特的從容——它不像臺北急於抹去過去，也不像臺南執著於古老。在臺中，眷村記憶、日治時代的工業遺產、與當代創意正在安靜地共存，形成一種沒有過度包裝的文化氛圍。\n\n臺中的文化村落型態與眾不同，這裡的「聚落」不是為了觀光而刻意打造的表演舞臺，而是真的有居民生活其中的活態社群。少了人潮的擁擠，多了時間流動的痕跡，這些地方適合慢下腳步，用一兩個下午好好感受。\n\n**審計新村**是許多人對臺中文創聚落的第一印象，但這裡近年來已經越來越擁擠。建議黃昏時刻造訪，人潮稍退的光影比較能感受到老眷村的氣氛。園區內的微型文創小店價格偏高，一杯手沖咖啡大約 NT$150-200，但空間規劃確實用心，保留了許多老屋的原始結構。\n\n**範特喜綠光計畫**位於美村路上，是用老眷村巷弄改造的微型聚落。這裡的店家替換頻率很高，能看到一些年輕創業者的實驗性作品。巷子裡的「草悟系」生活選物店值得一逛，價格比市區實惠許多，設計感也不馬虎。整體氛圍比審計新村安靜許多，適合喜歡慢慢逛、挖掘小物的旅客。\n\n**清水眷村文化園區**是相對冷門的選擇，卻是我個人最推薦的。這裡保留了完整的眷村格局，牆上還能看到老住戶的生活痕跡。園區定期有藝術進駐計畫，有時能遇到正在創作的藝術家聊聊。免門票，參觀時間約一小時。缺點是交通不便，開車比較方便。\n\n**梧棲文化出張所**是近期竄起的新景點，利用日治時期的警察宿舍群改造。這裡的建築修復得相當細緻，現場還提供免費的導覽服務（需提前預約）。週邊有一些小攤販和咖啡店，氣氛悠閒。門票 NT$50，可抵消費。\n\n**大甲車站周邊**是容易被忽略的文化角落。車站本身就是日治時代的建築，附近巷弄裡還保留著老商店和傳統理髮店。距離大甲鎮瀾宮步行約十分鐘，可以安排成宗教文化與老城區的半日遊。這裡沒有過度商業化，感受到的是真實的在地生活。\n\n【實用資訊】\n臺中市區往返各文化聚落建議租機車或開車，公共交通時間較長且班次不多。審計新村和範特喜綠光計畫可搭公車到「美村向上北路口」站；清水眷村建議自駕或搭乘區間車至清水站再轉計程車；梧棲文化出張所可搭乘臺中捷運至清水站再轉公車。多數聚落免費參觀，個別展覽或市集可能收取清潔費 NT$30-50。\n\n【旅遊小提示】\n平日上午多數店家休息，建議下午兩點後造訪。假日的市集人潮較多，想拍空景建議平日前往。臺中天氣炎熱，記得帶水和防曬。個人認為臺中文化聚落的價值不在「打卡」，而在感受一種慢慢生活的方式——這裡的節奏比臺北慢，比臺南現代，剛剛好的平衡正是它最迷人的地方。",
  "license": "CC BY 4.0"
}