{
  "title": "日月潭珍珠奶茶：跟著茶農走進臺灣高山茶的故鄉",
  "slug": "taiwan-dining-bubble-tea-sun-moon-lake-日月潭珍珠奶茶-跟著茶農走進臺灣高山茶的故鄉-fe0800",
  "industry": "dining",
  "category": "bubble-tea",
  "area": "sun-moon-lake",
  "url": "https://taiwan-encyclopedia.vercel.app/articles/taiwan-dining-bubble-tea-sun-moon-lake-日月潭珍珠奶茶-跟著茶農走進臺灣高山茶的故鄉-fe0800.html",
  "published": "2026-03-25",
  "quality_score": 7.5,
  "word_count": 1209,
  "tags": [
    "日月潭珍珠奶茶",
    "南投美食",
    "台灣手搖飲",
    "魚池鄉茶葉",
    "台茶18號"
  ],
  "content": "說到日月潭，多數人想到的是湖光山色和環潭腳踏車道，但許多人不知道的是——這裡其實是臺灣高山茶的重要產區。從魚池鄉一路延伸到海拔800至1200公尺的山區，茶園梯田層層疊疊，空氣中終年縈繞著烏龍茶的清香。正是這片富饒的茶葉故鄉，讓日月潭的珍珠奶茶擁有一種獨特的「茶底」優勢：用的是真正來自本地茶園的茶葉，而非一般連鎖店使用的進口茶葉。\n\n走進日月潭的珍珠奶茶店，你會發現一個有趣的現象選單上常見的不是傳統臺式奶茶的固定配方，而是直接標註「魚池紅玉」或「臺茶18號」——這些都是日月潭在地茶農種植的特色茶種。紅玉茶葉帶有天然的肉桂香與薄荷清涼感，搭配牛奶和珍珠後，層次分明，一點也不甜膩。這種「茶農直供」的模式，近年來在日月潭周邊的咖啡茶飲店迅速蔓延，成為當地Bubble Tea不同於都市連鎖店的核心差異化。\n\n如果你想品嚐最道地的日月潭風味，不妨從水社碼頭附近開始探索。這個區域是遊客最多的據點，聚集了多家由茶農轉型的茶飲店。這些店家的一大特色是會直接在店內展示茶葉罐，顧客可以看到茶葉的原始模樣，有些店家甚至提供茶葉試聞服務。\n\n另一個值得推薦的區域是向山遊客中心附近。這裡的珍珠奶茶店座位通常面向湖畔，許多人會點一杯珍珠奶茶搭配一份茶點，坐下來靜靜欣賞湖光山色。價格上，日月潭的珍珠奶茶平均單價落在新臺幣70至120元之間，比臺北都會區略低，但茶葉品質往往更好。如果你點的是使用紅玉茶底的品項，價格可能會稍微高一些，大約在新臺幣90至150元，但絕對值得一試。\n\n比較少人知道的是，伊達邵碼頭商圈其實藏著幾家沒有招牌的在地小店。這些店的裝潢簡單，沒有華麗的選單看板，卻有著最道地的手作珍珠。店家的珍珠是每天手工現做的，煮的時間控制的恰到好處，Q度適中且帶著淡淡的糖香。這種小店通常只在下午時段營業，錯過時間就吃不到了。\n\n最後要特別介紹的是位於玄奘寺周邊的茶飲店，這裡的店家主打「寺廟寧靜感」主題，座位區佈置得像是傳統茶席，搭配的茶點往往是本地茶農自製的茶梅或綠茶糕。許多在地人都說，這裡的珍珠奶茶喝起來特別「靜心」，或許是因為氛圍的關係，也或許是因為茶葉真的特別新鮮。\n\n實用資訊方面，從臺中高鐵站轉乘南投客運直達日月潭，車程約1.5小時，票價約新臺幣150元。如果自行開車，水社停車場每次收費新臺幣50元，假日人多建議提早出發。住宿方面，日月潭周邊的民宿從新臺幣1500元至5000元不等，建議選擇距離湖畔步道較近的住宿，這樣清晨或傍晚都可以悠閒散步。\n\n旅遊小提示：日月潭的珍珠奶茶，最好的品嚐時段其實是下午三點左右。那時候茶農剛把當天採摘的茶葉烘焙完成，茶葉的香氣正處於巔峰狀態，店家做出來的奶茶口感最為鮮活。另外，許多店家提供「無糖」或「少糖」選項，因為茶葉本身帶有自然的甜味與香氣，即使是無糖版本也不會覺得單薄。如果你對茶葉品種有興趣，可以直接詢問店家茶葉的來源，大部分的在地店家都樂於分享茶農的故事。",
  "license": "CC BY 4.0"
}