{
  "title": "花蓮寺廟巡禮：山海之間的心靈棲息地",
  "slug": "taiwan-tourism-temples-hualien-花蓮寺廟巡禮-山海之間的心靈棲息地-14de2a",
  "industry": "tourism",
  "category": "temples",
  "area": "hualien",
  "url": "https://taiwan-encyclopedia.vercel.app/articles/taiwan-tourism-temples-hualien-花蓮寺廟巡禮-山海之間的心靈棲息地-14de2a.html",
  "published": "2026-07-03",
  "quality_score": 6.5,
  "word_count": 1608,
  "tags": [
    "花蓮寺廟",
    "吉安慶修院",
    "花蓮旅遊",
    "宗教文化",
    "太魯閣"
  ],
  "content": "花蓮的寺廟與臺灣西部城鄉的喧鬧廟宇截然不同。這裡的宗教空間少了香火鼎盛的煙霧繚繞，多的是與山海對話的寧靜氛圍。從日治時期遺留的真言宗古剎，到當代結合人文關懷的靜修場域，花蓮的寺廟反映了這片土地上多元族群的信仰生活，也成為旅人在壯麗風景之外，另一個值得探索的心靈風景。\n\n花蓮寺廟的第一個獨特之處，在於它們與自然環境的緊密關係。太魯閣國家公園內的天祥佛寺，座落於立霧溪與塔次基裡溪交匯處的河階臺地上，四周被高山環繞，溪水聲常年相伴。另一個特色是族群與宗教的融合：阿美族、太魯閣族的原住民信仰，與漢人的佛教、道教、媽祖信仰在此交織，形成獨特的宗教景觀。此外，花蓮的寺廟建築往往蘊含日治時代的歷史記憶，尤其是吉安慶修院這樣的真言宗佛寺，更是理解花蓮殖民史的重要線索。\n\n說起花蓮最具代表性的寺廟，吉安慶修院絕對排在第一位。這座位於吉安鄉的日治時期真言宗佛寺，建於1917年，是當年日本移民村的重要信仰中心。現存的主殿保留了完整的日本佛教建築風格，殿內供奉的不動明王與弘法大師石像，帶有濃厚的江戶時期雕刻技法。平成年間被列為三級古蹟後，經過用心修復，庭院中的手水舍、 石碑與石燈都維持著原始風貌。慶修院最迷人的是其寧靜氛圍——遊客相對稀少（相較於北部的媽祖廟），可以慢慢欣賞日式建築的精緻細節，感受歷史在這裡留下的靜謐氣息。院方也保留了當年日本移民的文物展示間，值得細細觀覽。\n\n若想體驗當代花蓮的人文宗教精神，慈濟靜思堂是不可錯過的去處。這是慈濟功德會的發源地，由證嚴法師於1966年創立。靜思堂的建築外觀融合了現代簡約與傳統禪意，內部設有宗教藝術展覽空間，常態展出證嚴法師的著作與慈濟發展史。對遊客而言，靜思堂最特別的是提供靜心體驗活動——包括抄經、禪修體驗與人文講座。清晨的靜思堂園區尤其美麗，池畔的觀音雕像與遠方的中央山脈相映成趣，這是很多在地人都不知道的私房角落。\n\n位於花蓮市區的花蓮港天宮，則是理解花蓮海洋信仰的關鍵。這座供奉媽祖的廟宇建立於日治時期，是早期花蓮港（現在的花蓮港區）附近漁民與碼頭工人的信仰寄託。不同於西部沿海的大型媽祖廟，花蓮港天宮的規模較小，但香火持續百年不斷。廟內保留的古老神轎與匾額，見證了花蓮港口從日治到民國的發展歷史。每年媽祖生日的遶境活動，是花蓮市區難得的宗教盛事，隊伍會沿著舊港區一路行進，熱鬧而不失傳統韻味。\n\n喜歡深度文化探索的旅人，不妨往南走到富里。富里天主堂位於花蓮縣南端的富里鄉，是臺灣東部最具特色的原住民天主堂之一。這座由西班牙道明會神父興建於1950年代的天主堂，外觀採用了阿美族傳統茅屋的斜屋頂造型，內部裝飾則結合了原住民木雕與聖經故事壁畫。堂區的神父長期投入當地阿美族與客家社群的服務工作，近年更開放讓遊客參與彌撒與文化交流活動。這裡不是傳統意義上的「寺廟」，但它呈現了花蓮宗教多元性的另一個重要面向。\n\n前往花蓮參訪寺廟，交通需要一些規劃。自行開車是最彈性的方式，從花蓮市區到吉安慶修院約15分鐘車程，到天祥則需約1.5小時（途經太魯閣國家公園）。搭乘公車的話，花蓮火車站有往太魯閣的班車可達天祥，吉安慶修院可搭乘花蓮客運至吉安鄉公所站步行抵達。慈濟靜思堂位於花蓮市區，距離火車站約3公里，可搭計程車或騎租借的腳踏車前往。\n\n大部分花蓮寺廟參觀都是免費的，只有吉安慶修院收取 NT$30 的清潔維護費。慈濟靜思堂的靜心體驗活動（如抄經）通常需要提前預約，費用視活動內容而定。整體而言，花蓮寺廟的參訪成本遠比西部熱門廟宇低許多，也沒有過度商業化的紀念品攤位問題。\n\n幾個實用的小提醒：花蓮的山區天氣變化快，前往天祥記得攜帶雨具。吉安慶修院夏季蚊蟲較多，建議噴防蚊液。慈濟靜思堂的宗教體驗活動名額有限，強烈建議提前在慈濟官網查詢並預約。如果想感受花蓮寺廟最寧靜的一面，清晨七點前抵達是最推薦的時段——這個時候的光線柔和，遊客稀少，能夠真正體會山海之間的宗教靜謐。",
  "license": "CC BY 4.0"
}