{
  "title": "高雄海港體驗：從賞鯨幻想到港灣深度旅遊",
  "slug": "taiwan-tourism-whale-watching-kaohsiung-高雄海港體驗-從賞鯨幻想到港灣深度旅遊-6f2eff",
  "industry": "tourism",
  "category": "whale-watching",
  "area": "kaohsiung",
  "url": "https://taiwan-encyclopedia.vercel.app/articles/taiwan-tourism-whale-watching-kaohsiung-高雄海港體驗-從賞鯨幻想到港灣深度旅遊-6f2eff.html",
  "published": "2026-06-22",
  "quality_score": 6.5,
  "word_count": 2126,
  "tags": [
    "高雄海上體驗",
    "旗津渡輪",
    "愛河夜航",
    "港都文化",
    "高雄自由行"
  ],
  "content": "說起高雄的海上活動，許多遊客第一個想到的是賞鯨——但讓我誠實地告訴你，高雄並不是臺灣賞鯨的理想地點。臺灣賞鯨的熱點集中在花蓮和臺東的太平洋海域，那裡才有較高的鯨豚出沒率。相比之下，高雄海域賞鯨的成功率偏低，許多標榜「高雄賞鯨」的行程，其實是將遊客載到外海後，主要看到的仍是海豚，甚至有不少是「空軍」（看不到任何鯨豚）的情況。\n\n然而，這並不意味著高雄的海上體驗不值得期待。相反地，這座從重工業蛻變而來的港都，有著豐富多元的海洋文化內涵，只是一般旅遊書很少告訴你罷了。作為曾經的遠洋漁業重鎮，高雄擁有深厚的漁業傳統，而愛河、西子灣、旗津、港區沿岸構成的水岸線，更藏著許多值得探索的面向。\n\n## 高雄海上體驗的真正亮點\n\n既然傳統賞鯨不是高雄的強項，這座城市真正值得推薦的，是以下幾種獨特的海上體驗：\n\n### 1. 旗津渡輪體驗\n\n旗津是高雄最經典的水岸符號，而渡輪是最具港都風情的交通工具。從鼓山渡輪站到旗津渡輪站，單程票價僅需新臺幣50元（機車加20元），航程約10分鐘。這條航線不只是交通，更是觀賞高雄港灣景觀的最佳視角——你可以在船上看到85大樓、港口吊臂、來往的貨輪，感受這座國際商港的氣勢。建議選擇傍晚時段搭乘，夕陽下的旗津渡輪是instagram上被瘋傳的經典畫面。\n\n旗津本身也值得花上半日探索：旗津天后宮是當地信仰中心，旗津海水浴場適合戲水，炮臺古蹟訴說著過去的軍事歷史，而海產街的現撈海鮮更是不能錯過。傍晚在旗津海邊散步，看著港區夕陽漸漸沉入海平面，那是高雄才能體會的浪漫。\n\n### 2. 愛河夜航體驗\n\n如果說旗津展現的是高雄的漁業過去，愛河夜航呈現的就是這座城市的現在與未來。愛河，全長約12公里，穿越高雄市區心臟地帶，曾經是工業排水溝，如今是城市綠肺與浪漫地標。\n\n愛河夜航的行程從真愛碼頭或光榮碼頭出發，沿途經過中正橋、願景橋、七賢橋，船長會導覽沿岸建築與橋梁的歷史。票價約新臺幣250-350元，航程50分鐘至70分鐘。最推薦的時段是傍晚5點半出發，這樣可以在船上看到白天與夜晚的轉換——天色漸暗時，兩岸路燈與大樓燈光倒映在河面上，是這座城市最溫柔的樣貌。\n\n近期愛河夜航更結合了水上SUP立槳體驗，讓不會划船的遊客也能在專業教練帶領下體驗劃槳的樂趣，適合想嘗試水上活動但不敢冒險的家庭遊客。\n\n### 3. 港區碼頭散步與文化導覽\n\n高雄港區近年積極轉型成為文化觀光區，棧貳庫、棧伍庫、高雄港史館、85大樓觀景臺等，都是認識這座城市的絕佳起點。\n\n棧貳庫（Kaohsiung Pier-2）位於香蕉碼頭旁，是日治時期的舊倉庫群改造成的文創商場，保有原始的結構與風貌，裡面進駐了質感選物店、咖啡廳與餐廳。棧伍庫則定位為海洋教育與體驗空間，常舉辦海洋相關展覽與工作坊。\n\n高雄港史館（現在的高雄市立歷史博物館）則是瞭解這座城市海洋身世的最佳去處。這棟建於1919年的和洋折衷式建築，原本是高雄港務局的辦公室，記錄了高雄從小漁村發展成國際大港的完整歷程。門票僅需新臺幣30元，展覽品質出乎意料地高。\n\n### 4. 蚵仔寮漁港體驗\n\n如果想要更接地氣的海洋體驗，位於梓官區的蚵仔寮漁港是內行人的私房景點。這裡是高雄最熱鬧的現撈魚市場，每天清晨與傍晚的拍賣時間，魚市場裡充滿了討價還價的熱鬧氛圍。\n\n遊客可以在這裡直接購買最新鮮的海產，請附近餐廳代客料理。蚵仔寮的蝨目魚、午仔魚、紅蟳都是當季限定的美味。附近還有養殖蚵田，可以體驗剖蚵樂趣。這個景點沒有過度包裝，保留了濃濃的漁村風情，適合想遠離觀光客人潮、追求真實體驗的旅人。\n\n## 實用資訊\n\n### 交通方式\n- 旗津渡輪：捷運至「鼓山站」或「西子灣站」，步行至鼓山渡輪站。\n- 愛河夜航：捷運至「市議會站」或「愛河之心」站，步行至真愛碼頭或光榮碼頭。\n- 棧貳庫：捷運至「鼓山站」或「西子灣站」。\n- 蚵仔寮漁港：開車或騎機車從市區約30分鐘；也可搭乘公車至梓官區公所站。\n\n### 費用參考\n- 旗津渡輪：單程50元，來回90元\n- 愛河夜航：250-350元\n- 愛河水上SUP：400-600元\n- 棧貳庫：免門票（部分展覽需購票）\n- 高雄港史館：30元\n- 蚵仔寮魚市場：免門票\n\n### 營業時間\n- 旗津渡輪：24小時（尖峰時段約15-20分鐘一班）\n- 愛河夜航：通常下午至晚間，須提前預約\n- 棧貳庫：10:00-18:00（週三四公休）\n- 高雄港史館：09:00-17:00（週一公休）\n\n## 旅遊小提示\n\n1. 渡輪建議選傍晚時段，不只光線好，回程還能趕上85大樓的夜景。\n2. 愛河夜航務必提前預訂，假日一位難求。\n3. 蚵仔寮魚市場清晨5-7點、傍晚4-6點最熱鬧，想體驗拍賣過程要早起。\n4. 高雄海上活動的最佳季節是4-10月，冬季東北季風影響渡輪航班與夜航體驗。\n5. 如果真的非常想看鯨豚，建議安排一日遊前往花蓮或臺東，那裡的賞鯨成功率高出許多。\n\n高雄的海上魅力，從來不在於「賞鯨」這個標籤，而在於這座城市花了數十年時間，從一個工業港口蛻變成能夠悠閒漫步、細細品味的灣岸城市。誠實面對地理條件的限制，才能真正發現高雄的與眾不同。",
  "license": "CC BY 4.0"
}