{
  "title": "臺北珍珠奶茶選購指南：從50元到200元的價格地圖與消費邏輯",
  "slug": "taiwan-dining-bubble-tea-taipei-臺北珍珠奶茶選購指南-從50元到200元的價格地圖與消費邏輯-f88bf4",
  "industry": "dining",
  "category": "bubble-tea",
  "area": "taipei",
  "url": "https://taiwan-encyclopedia.vercel.app/articles/taiwan-dining-bubble-tea-taipei-臺北珍珠奶茶選購指南-從50元到200元的價格地圖與消費邏輯-f88bf4.html",
  "published": "2026-07-06",
  "quality_score": 7.5,
  "word_count": 1298,
  "tags": [
    "台北珍珠奶茶",
    "台北手搖茶",
    "台北茶飲推薦",
    "台北美食",
    "台灣珍珠奶茶"
  ],
  "content": "說起珍珠奶茶，臺北是所有茶飲愛好者的必修課。這裡不僅是全球手搖茶的發源地，更是觀察臺灣茶飲產業演變的最佳場域。從1980年代春水堂在臺中發明瞭第一杯珍珠奶茶開始，這項臺式飲品已經走進全球每一個主要城市，但在臺北，你依然能找到最完整的茶飲生態系——從巷口平價老店到質感精品茶屋，每一個價格帶都代表著不同的消費場景與生活態度。\n\n來臺北喝珍珠奶茶，第一件事要搞懂的就是「價格分層」。這不是單純的貴或便宜，而是反映出完全不同的產品定位與體驗追求。\n\n**50-70元區間：經典平價老店**\n\n這個價位帶是臺北最多「隱藏版高手」的戰區。許多在補習街、傳統市場周邊存活超過二十年的老店，靠的不是華麗裝潢，而是扎實的茶底與實惠的價格。這些店家的珍珠通常是自己熬煮的，黑糖香氣濃郁且帶有微微的焦糖感，甜度固定但恰到好處。招牌奶茶的茶味通常較重，奶精使用量適中，喝起來有種「古早味的踏實感」。這個區間的店家主要服務在地學生與上班族，忙碌時外帶一杯，剛好補充下午的電力。\n\n**70-120元區間：文青風格茶飲**\n\n這是近年臺北茶飲競爭最激烈的價位帶，也是最多創新口味與設計風格出現的戰場。走進這個價位的店家，你會發現選單上除了經典奶茶，往往還會有季節限定水果茶、奶蓋系列、或是加入燕麥奶、植物奶的創意配方。這些店面的裝潢通常比較有設計感，適合內用拍照，目標客群是追求新鮮感與社群分享價值的年輕人。值得一提的是，這個價位的「配料」選擇也更加豐富，從傳統珍珠、椰果到現在流行的寒天、愛玉、芝士奶蓋都有機會見到。\n\n**120-200元區間：精品茶屋體驗**\n\n這個價位帶的珍珠奶茶，已經從「解渴飲品」升級為「精品體驗」。使用的茶葉通常是梨山、阿里山等高山產區的單品茶葉，牛奶可能選用在地小農鮮奶或是進口品牌，珍珠的品質與口感也更講究——有些店家甚至提供「白玉珍珠」或「黑糖珍珠」等不同選擇。在這些店裡，珍珠奶茶更像是一杯需要細細品味的茶飲，製作過程講究茶湯溫度、奶香比例與珍珠Q度的平衡。內用空間通常舒適有質感，適合想要好好坐下來享受一杯好茶的消費者。\n\n**選擇臺北珍珠奶茶的小技巧**\n\n如果是為了「懷唸的味道」，直接往傳統市場或老社群周邊找，問當地人最準。如果是追求「拍照打卡的網紅款」，信義區、大安區或赤峰街一帶的文青茶飲店可以參考。如果是「認真喝茶」，不妨選擇有清楚標示茶葉產地與品牌精神的精品茶屋。\n\n另外，臺北的珍珠奶茶店密度極高巷戰激烈，有些店家會推出「加珍珠不加價」或「第二杯半價」的優惠，靠近下班或打烊前去詢問，往往能撿到便宜。有些老店週末會提早打烊，建議避開週一公休日。\n\n**實用資訊**\n\n臺北珍珠奶茶的價格大約在NT$50-200之間，視店家定位與配料選擇而定。全年四季都有營業，但夏季天氣炎熱時，冰飲需求特別高，可能需要排隊等候。大部分店家營業時間從上午10點到晚上9點或10點，熱門時段是下午2-5點。交通方面，捷運沿線幾乎都有茶飲店分佈，非常方便。\n\n來臺北喝珍珠奶茶，重點不在於追隨網紅名店，而是找到適合自己當下需求的那一杯。這個城市的迷人之處，就在於它能容納每一種喝茶的姿態。",
  "license": "CC BY 4.0"
}