{
  "title": "日月潭數位旅遊攻略：讓科技為湖畔之旅加分的體驗指南",
  "slug": "taiwan-shopping-electronics-sun-moon-lake-日月潭數位旅遊攻略-讓科技為湖畔之旅加分的體驗指南-6ca7a8",
  "industry": "shopping",
  "category": "electronics",
  "area": "sun-moon-lake",
  "url": "https://taiwan-encyclopedia.vercel.app/articles/taiwan-shopping-electronics-sun-moon-lake-日月潭數位旅遊攻略-讓科技為湖畔之旅加分的體驗指南-6ca7a8.html",
  "published": "2026-06-06",
  "quality_score": 7.5,
  "word_count": 2086,
  "tags": [
    "日月潭",
    "數位旅遊",
    "智慧旅遊",
    "租借服務",
    "GoPro"
  ],
  "content": "說到日月潭，大多數人想到的是搭船遊湖、騎單車環湖，或是欣賞湖畔的日出日落。但你知道嗎？在這個以自然風光聞名的旅遊勝地，科技也能為你的旅程帶來不一樣的體驗。\n\n這篇文章不談傳統的電子產品採購，而是從「數位體驗」的角度，帶你看日月潭周邊有哪些科技服務可以讓你的旅行更加便利，甚至成為旅程中的獨特回憶。\n\n## 日月潭的數位旅遊新浪潮\n\n近年來，日月潭積極推動智慧旅遊，從腳踏車道的電子導覽到湖畔的AR互動體驗，科技元素悄悄融入了這個傳統風景區。特別是2023年後，隨著疫情後旅遊型態的改變，越來越多遊客重視「無紙化旅遊」和「即時資訊取得」，日月潭周邊的數位服務也因此蓬勃發展。\n\n不同於都會區的電子產品專賣店，日月潭的科技服務更強調「為旅遊體驗加分」——這裡沒有大型3C賣場，但有專為旅人設計的數位租借服務與即時維修支援。\n\n## 推薦體驗點\n\n### 1. 日月潭遊湖電子語音導覽租借\n\n位於水社碼頭附近的遊湖資訊服務站，提供多語言語音導覽裝置租借。這不是傳統的導覽機，而是結合手機App的智慧導覽系統，租用後可獲得專屬的導覽QR Code，掃描後即可透過手機接收即時解說。\n\n特色在於「走到哪講到哪」的功能——系統會根據你的GPS位置自動播放相關介紹，無需按鍵操作。對於喜歡自由行的遊客來說，這讓你可以用自己的節奏探索湖畔風光，同時又不錯過任何文化知識。\n\n租借費用約NT$150-200，可使用整天。裝置需要押證件，歸還時退回。建議提早預約，旺季常一位難求。\n\n\n### 2. GoPro運動相機租借——記錄你的湖上冒險\n\n日月潭的湖上活動豐富，從立槳、獨木舟到遊艇求婚，這些精彩時刻值得用更好的畫質記錄。位於朝霧碼頭的戶外用品店提供GoPro相機租借服務，這是當地戶外活動愛好者口耳相傳的隱藏服務。\n\n相較於一般手機，GoPro的超廣角鏡頭更能捕捉湖面寬廣的景色，防水特性也適合水上活動。店家常備多臺現貨，並提供簡易教學，租借費用依機型從NT$300-500/天不等。\n\n老闆本身是日月潭在地的水上活動玩家，會根據你的行程推薦適合的拍攝角度，這種「玩家推薦玩家」的服務模式，是都市3C賣場感受不到的。\n\n### 3. 湖畔發呆亭AR互動體驗\n\n近年日月潭設定了多處結合擴增實境(AR)的互動裝置藝術，最知名的是水社碼頭與向山遊客中心周邊的「發呆亭」AR體驗。遊客下載特定App後，對著發呆亭掃描，即可看到虛擬的日月潭故事角色現身，甚至出現日月潭傳說中的邵族達瑪拉公主。\n\n這項體驗完全免費，是在地推動文化科技的成果。雖然技術層面不如都會區的VR體驗來得華麗，但結合了在地邵族文化元素，提供了獨一無二的文化體驗。適合親子同遊，讓孩子透過科技認識原住民文化。\n\n### 4. 單車智慧導航系統租借\n\n日月潭環湖腳踏車道被CNN評為全球第二大最美腳踏車道，如果你打算環湖，強烈建議租借具備智慧導航功能的腳踏車碼表。\n\n位於向山腳踏車道入口處的單車店有提供這項服務，裝置可即時顯示騎乘距離、速度，並內建環湖各處的景點介紹。最大的特色是「語音導航」——騎到叉路時會自動語音提醒，不用停下來看地圖。\n\n租借費用約NT$100-150/天，依機型不同。建議清晨或傍晚租借，氣溫舒適且光線適合拍照。\n\n### 5. 手機行動電源快速救援服務\n\n在風景區手機沒電是每個旅人的惡夢。水社公有停車場旁的手機配件店提供「快速救援」服務——如果你忘記帶行動電源或充電線，可以緊急租借或購買。\n\n這裡的價格比機場略高，但急難時的方便性無價。店家也提供的手機簡易防水套租借，對於準備搭船遊湖的遊客相當實用。\n\n費用約NT$50-100的即時租借費，購買則依品項而定。這種「旅人救急」型別的服務，在日月潭這種大型風景區特別受到歡迎。\n\n## 實用資訊\n\n**交通方式**：從臺中高鐵站搭乘南投客運至日月潭，車程約1.5小時；或從臺中火車站搭乘臺灣好行巴士。自駕的話，環湖公路全線約30公里，停車場多分佈在各碼頭區域。\n\n**費用參考**：數位導覽租借NT$150-200、GoPro租借NT$300-500/天、單車碼表NT$100-150/天、行動電源即時救援NT$50-100。整體花費視個人需求而定。\n\n**營業時間**：各店家營業時間多為08:00-17:00，旺季可能延長。建議避開中午時段辦理租借，人潮較少。\n\n**最佳季節**：全年皆適合，但冬季清晨有霧，數位裝置操作需注意防潮；夏季則要注意防曬與裝置過熱問題。\n\n## 旅遊小提示\n\n1. 日月潭山區天候變化快速，電子裝置建議隨身攜帶防潮袋\n2. 旺季(暑假、春節)各項租借服務人潮眾多，建議提早預約或選擇非假日\n3. 部分體驗需要先下載App，建議在有網路時先完成下載，山區部分割槽域訊號較弱\n4. 湖畔夜景別有風味，如果有夜遊計劃，記得先確認手機電量\n5. 當地店家普遍可使用Line Pay、街口支付等行動支付，但小額消費仍建議隨身攜帶少許現金\n\n來日月潭，不只是用眼睛看風景，更可以讓科技成為你探索這片美麗湖光山色的最佳夥伴。",
  "license": "CC BY 4.0"
}