{
  "title": "臺南郊山步道：府城周邊的山林文化深度遊",
  "slug": "taiwan-tourism-mountain-trails-tainan-臺南郊山步道-府城周邊的山林文化深度遊-661098",
  "industry": "tourism",
  "category": "mountain-trails",
  "area": "tainan",
  "url": "https://taiwan-encyclopedia.vercel.app/articles/taiwan-tourism-mountain-trails-tainan-臺南郊山步道-府城周邊的山林文化深度遊-661098.html",
  "published": "2026-06-05",
  "quality_score": 6.5,
  "word_count": 1879,
  "tags": [
    "台南登山",
    "郊山步道",
    "府城後山",
    "白河步道",
    "左鎮化石"
  ],
  "content": "說到臺南，大多數人先想到的是牛肉湯、碗粿和古蹟，但其實從市中心出發不到一小時，就能走進完全不同的山林世界。臺南的郊山步道特別之處不在於高度——這裡沒有三千公尺的高山稜線——而在於它們與聚落、廟宇、產業遺址的深刻連結。爬山之餘，還能走進一段被時間沉澱的文化記憶。\n\n臺南的山區主要分佈在東部的白河、左鎮、楠西、官田一帶，屬於阿里山山脈的延伸丘陵。這些步道的特色是「低海拔、高文化」——步道不長，難度適中，但沿途常有古井、砌石駁坎、土地公廟，甚至是日治時期的產業遺址。對於想要親近自然但又不喜歡高強度登山的人來說，這裡是完美的入門選擇。\n\n【推薦地點】\n\n**一、大凍山步道（白河）**\n\n大凍山是臺南最高峰，海拔1241公尺，但步道規劃完善，從白河區的關嶺裡出發，沿途多為石階和木棧道，單程約2.5公里，來回需3至4小時。這裡最特別的是「芒花隧道」——秋冬時節，芒草高過人身，走在步道上彷彿穿越一條金色長河。山頂觀景臺可俯瞰嘉南平原，天氣清朗時甚至看得到臺灣海峽。清晨或傍晚上山，光線柔和，拍照效果最佳。步道入口有簡易廁所和休息區，但山上沒有賣店，建議自備飲水與行動糧。\n\n**二、烏山嶺步道（楠西）**\n\n烏山嶺步道橫跨臺南與嘉義，是早年「三條崙古道」的一部分，全長約4公里，沿途可見儲存良好的砌石駁坎和石橋，這些是清代先民引水灌溉的智慧結晶。步道中段有一座小型土地公廟，當地人稱「伯公」，據說求籤很靈驗，常有登山客專程前來參拜。終點是一片孟宗竹林，竹林倒影與石階構成天然禪意場景，是攝影愛好者的私房景點。這裡的亮點是「古道產業文化」——不只是爬山，而是在走路的過程中理解先民如何在山區生活。\n\n**三、左鎮化石區步道（左鎮）**\n\n左鎮是臺灣重要的化石產地，步道設計將自然地質與科普教育結合。沿途設有解說牌，說明二千多萬年前，此地曾是海底競技場，珊瑚礁化石、貝類化石隨處可見。步道不長，約1.5公里，適合親子同遊。園區內的「化石館」展示當地挖掘的鯊魚牙齒、珊瑚礁等標本，門票僅50元，是少數需要購票入園的臺南郊山步道。這裡的獨特在於「地球記憶」——爬山的同時也在閱讀一部跨越千萬年的地質史書。\n\n**四、曾文水庫環湖步道（官田）**\n\n曾文水庫是臺南最大的水庫，環湖步道約8公里，分為好幾段，可根據體力選擇走完全程或精華段。沿途設有多處觀景臺，最著名的是「玉山觀景臺」，天氣好時可看到玉山群峰倒映水中——這是臺灣少數能在低海拔觀賞高山倒影的地點。步道旁常有ukai本土鳥類，運氣好能看到大冠鷲盤旋。這裡的亮點是「湖光山色」——不同於一般郊山的叢林景觀，水庫的開闊水域提供不一樣的視覺享受。早晨霧氣瀰漫時，更有如人間仙境。\n\n**五、麒麟山步道（白河）**\n\n麒麟山步道位於白河區的火山碧雲寺附近，是一條結合宗教文化的步道。從碧雲寺出發，沿途可見姿態各異的石雕觀音，沿著產業道路蜿蜒而上，終點是一座小祠，供奉觀音佛祖。整條步道不長，約2公里，來回1.5小時，但香火鼎盛，常有信眾專程前來祈福。這裡的特別之處在於「宗教登山」——不是純粹的運動健身，而是在山林中尋求一份寧靜與心靈慰藉。建議清晨前往，寺廟的晨鐘與鳥鳴交織，是城市中感受不到的體驗。\n\n【實用資訊】\n\n交通方式：臺南市區前往各郊山步道建議自駕或包車。從臺南火車站開車至白河約40分鐘，至左鎮約50分鐘，至楠西約1小時。公共運輸部分，搭乘大臺南公車「黃線」可達白河市區，再轉乘計程車前往步道入口，但班次較少，建議提前查詢時刻表。\n\n費用：大凍山、烏山嶺、麒麟山步道均免費進入；左鎮化石區門票50元；曾文水庫入園費200元（含水庫遊艇體驗）。停車費部分，碧雲寺前停車場免費，大凍山第二停車場每次50元。\n\n營業時間：各步道均為24小時開放，但建議日間前往。左鎮化石區開放時間為08:00-17:00（週一休館）。曾文水庫開放時間為08:00-17:30。\n\n最佳季節：秋季（10月至12月）最適合登山，天氣涼爽，芒花盛開。冬季（12月至2月）清晨有霧，景觀夢幻但要注意保暖。夏季（6月至9月）天氣炎熱，建議清晨或傍晚上山，並注意防蚊。\n\n【旅遊小提示】\n\n臺南郊山步道與北部郊山最大的不同在於「距離」——從市中心出發，一小時內就能從繁華走進山林。這裡不要求體能極限，而是強調文化深度。建議把步道與附近的古蹟或美食結合：爬完大凍山，可以在白河市區吃一碗碗粿；走完烏山嶺，到楠西品嚐梅子料理。左鎮化石區距離臺南市區不遠，適合安排半日遊。穿著方面，建議穿抓地力好的運動鞋或登山鞋，山區午後常有陣雨，路面濕滑。",
  "license": "CC BY 4.0"
}