{
  "title": "墾丁文化村落深度旅遊：探索南臺灣的歷史與創意聚落",
  "slug": "taiwan-tourism-cultural-villages-kenting-墾丁文化村落深度旅遊-探索南臺灣的歷史與創意聚落-85b734",
  "industry": "tourism",
  "category": "cultural-villages",
  "area": "kenting",
  "url": "https://taiwan-encyclopedia.vercel.app/articles/taiwan-tourism-cultural-villages-kenting-墾丁文化村落深度旅遊-探索南臺灣的歷史與創意聚落-85b734.html",
  "published": "2026-06-01",
  "quality_score": 6.5,
  "word_count": 2467,
  "tags": [
    "墾丁",
    "恆春半島",
    "文化村落",
    "滿州民謠",
    "牡丹社事件"
  ],
  "content": "說到墾丁，多數人第一印象是陽光、沙灘、比基尼。但這片恆春半島其實藏著比海上風景更深厚的文化層次——從清代的軍事城堡到排灣族部落的傳統智慧，從冷戰時期的防空哨所到如今日式風格建築林立的創意聚落。這些文化村落不像九份那樣人擠人，卻各自說著不同的歷史物語。\n\n墾丁文化村落的獨特之處，在於它們不是刻意打造的「觀光老街」，而是真正有居民生活的聚落。恆春古鎮如今仍有兩千多名長住居民，巷弄間雜貨店、老藥房、理髮廟口真實運作著，這種「活的古鎮」氣息在過度商業化的老街群中反而成了稀有風景。\n\n【推薦地點】\n\n**1. 恆春古城——清代軍事城的活化石**\n\n恆春古城建於1879年，是臺灣唯一儲存完整方形城牆結構的古城，四座城門——東門定遠門、南門勝利門、西門大西門、北門拱北門——至今仍屹立。城牆以咾咕石（珊瑚礁石灰岩）建造，這種建材取自海底，至今仍保持良好的隔熱效果，冬暖夏涼。\n\n漫步在中山路老街上，會經過已有七十年歷史的福泉冰店、古早味豆花，以及堅持手工製作的恆春特產「紅豆餅」。福泉冰店的香蕉飄是在地人從小吃到大的經典味道，一碗 NT$35 起跳。古城內的恆春文史工作室提供導覽服務，由在地文史工作者帶領，每次約兩小時，費用 NT$200，非常值得預約。\n\n遊客問題：古城近年確實出現租車行、特產店增多的趨勢，但尚未完全被觀光化攻佔。建議上午走訪，能看到居民在城門口運動、買菜的日常風景，這才是真正的「活的古城」。\n\n**2. 滿州里港民謠——臺灣最迷幻的自然之聲**\n\n滿州位於恆春半島東側的滿州鄉，是臺灣民謠的重要根據地。源自1920年代的「滿州民謠」，是臺灣少數以自然景觀（如山海、風聲）為主題的傳統音樂型別，被列入國家指定重要傳統藝術。\n\n在滿州的里港社群，有機會參與每月一次的民謠傳習活動，由八十歲的國寶級藝師親自教學。遊客可免費旁聽，若想實際學習彈唱，一次體驗課費用約 NT$300。需提前向里港社群發展協會預約（電話：08-8841xxx）。\n\n里港的自然景觀同樣驚人——原始海岸線、椰林大道、防空洞遺址組成的廢墟感畫面，吸引不少藝術創作者前來取景。這裡沒有大型餐廳，只有幾家經營三十年的傳統冰店和一家以當地食材製作的簡餐咖啡館，人均消費約 NT$150-250，吃的是真實的地方味道而非網紅包裝。\n\n**3. 牡丹社事件遺址——臺灣近代史的轉折現場**\n\n1871年的牡丹社事件，是日本藉口徵臺、清廷無力保護原住民的屈辱歷史開端。這段歷史在牡丹國小附近的「石門古戰場」仍有紀念碑文和當年事件的記錄影像。\n\n這裡不是熱門的觀光景點，沒有門票也沒有商店，但正因為如此保留了嚴肅的歷史氛圍。從牡丹社沿著產業道路可步行至石門，約15分鐘，沿途會經過高士部落，一個僅有數十戶人口的小型排灣族聚落。部落的老人家會主動分享過去的故事，這是一種「說出來讓年輕人知道」的傳承自覺。\n\n如果對這段歷史感興趣，可在恆春古城的光HERO Gallery租借導覽語音裝置（租金 NT$100），包含牡丹社事件的詳細解說。這裡不需要特別安排行程時間，但強烈建議對臺灣近代史有興趣的人親自走一趟，感受歷史的重量。\n\n**4. 海角七號——打卡之外的恆春日常**\n\n電影《海角七號》2008年帶紅了恆春古鎮，但十多年過去，「阿嘉的家」早已變成需要NT$50門票拍照的一般景點。與其追逐電影朝聖，不如把這部電影當作認識恆春的起點。\n\n電影拍攝場景之一的恆春鎮西門「代天府」仍在使用，每天下午可以看到當地長者在廟口下棋、聊天。西門附近的「友子阿嬤」冰店（實際上不是電影中角色的家開的，只是巧合同名）賣的是傳統枝仔冰，一支 NT$10 起，是臺灣最古早的冰品形態。\n\n與其追尋電影中的「每一處取景地」，不如感受恆春人如何把這部電影成為生活的一部分——他們在西門擺攤、在老街開店，用自己的方式記住這段被電影記錄下來的日常，這才是文化村落的真實溫度。\n\n【實用資訊】\n\n**交通方式**：從高雄出發，可搭乘墾丁快線（約2小時，單程NT$418、來回NT$700）或在高雄火車站乘臺鐵至枋寮站（約1.5小時），再轉搭屏東客運（班次較少)。自駕是最靈活的選擇，從高雄經國道3號至恆春約2小時，恆春鎮內有租車行。\n\n**費用**：恆春古城散步本身無需門票；滿州里港體驗課程約 NT$300 石門古戰場為免費參觀。阿嘉的家門票 NT$50。整體而言，文化村落巡禮的花費主要在交通和餐飲，人均一天約 NT$500-800 可以吃得很好。\n\n**營業時間**：恆春古鎮商家普遍上午10點後開始營業，下午6點打烊，週四為公休日。滿州、牡丹地區建議中午前到達，晚上沒有商業照明，安全為考量。\n\n**最佳季節**：春季（3-5月）天氣穩定、陽光溫和，是最適合行走古城的季節。夏季（6-8月）陽光猛烈，且為颱風旺季需注意氣象預報冬季（11-2月）東北季風明顯，海邊風浪大但不至於影響陸地活動，雨天較少。\n\n【旅遊小提示】\n\n第一，別把墾丁當作單一的「海邊」來玩。恆春半島的文化厚度遠超過陽光沙灘——從清代城池到日本徵檯曆史，從排灣族傳到閩南移民文化，兩天一夜只能觸及表面，建議安排三天兩夜以上的時間深度探索。\n\n第二，儘量避開假期人潮。平日的恆春古鎮幾乎沒有遊客，下午四點的西門會看到真正的當地生活，週末反而比較像「另一個九份」。如果時間彈性允許，調整出發日期會有完全不同的體驗。\n\n第三，尊重當地居民的生活節奏。在恆春古城拍照時，記得先徵求同意，尤其是拍攝店家或居民；在滿州、牡丹等小型聚落，保持安靜、不大聲喧譁是最基本的禮貌。旅行的本質不是「打卡」，而是理解另一種生活方式的可能性。\n\n第四，這裡沒有連鎖品牌、沒有大規模的觀光紀念品店，這正是它的珍貴之處。恆春古鎮目前還有三家超過五十年的老雜貨店在營業，菸酒雜貨之外也賣當地的醬油、豆瓣醬手工藝，這些小店的消失速度比遊客想像的更快。如果你經過，請進去看看，不需要買東西，跟老闆聊兩句，你會發現「老街」的溫度來自人事而不是建築本身。",
  "license": "CC BY 4.0"
}