{
  "title": "臺北非典型 Live 場域：高空酒吧、Jazz 酒吧與隱藏版音樂地圖",
  "slug": "taiwan-entertainment-live-performances-taipei-臺北非典型-live-場域-高空酒吧-jazz-酒吧與隱藏版音樂地圖-be2281",
  "industry": "entertainment",
  "category": "live-performances",
  "area": "taipei",
  "url": "https://taiwan-encyclopedia.vercel.app/articles/taiwan-entertainment-live-performances-taipei-臺北非典型-live-場域-高空酒吧-jazz-酒吧與隱藏版音樂地圖-be2281.html",
  "published": "2026-07-07",
  "quality_score": 6.5,
  "word_count": 1878,
  "tags": [
    "台北現場表演",
    "台北夜生活",
    "Jazz酒吧推薦",
    "高空酒吧",
    "台北文創園區"
  ],
  "content": "說到臺北的現場表演，你腦中第一個浮現的是什麼？是西門町的 LIVE WAREHOUSE 還是華山的 Revolver？這些傳統 Live House 當然值得一去，但臺北的音樂場景遠比你想的更豐富。其實，這座城市的表演空間散佈在巷弄裡的 Jazz 酒吧、高樓層的景觀餐廳，甚至是文創園區的露天廣場。來臺北玩，與其只追著名Live House跑，不如把腳步放慢，看看這些「非典型」的演出場所。\n\n**臺北的 Live 場域有什麼不一樣？**\n\n臺北的現場展演空間發展得比中南部更加多元，這裡不只是搖滾樂團的天下。飯店高空酒吧、專業 Jazz 酒吧、文創園區，這些非典型場地近年來吸引了不少喜歡「氣氛感」的觀眾。相較於高雄的戶外場地特色，臺北的優勢在於選擇多元——從免費的露天音樂會到票價破千的高階表演都有。當然，臺北的票價也確實比中南部略高，一場普通規格的演出票價大約在 NT$300-800 元之間，高階表演或國外藝人陣容則可能突破 NT$1,500。\n\n**高空酒吧的星光音符**\n\n如果你是那種「看錶演要有 view」的人，臺北的高空酒吧絕對不會讓你失望。位於信義區的 CAPTAIN  STAG  (君悅酒店) 每到週末常有現場爵士樂演出，一邊喝著 NT$400 起跳的調酒，一邊俯瞰 101 大樓的夜景，視覺聽覺一次滿足。這種場合適合約會或慶祝特別日子，穿著可以稍微講究一點。另一個選擇是 inhouse 的 MARSALIS  HOME，不定期有爵士鋼琴手的演出，氣氛相對私密，適合想要好好享受音樂的兩三人小聚。\n\n**巷仔內的 Jazz 秘密基地**\n\n真正的音樂老饕會告訴你，臺北最道地的 Jazz 表演其實藏在民生社群和東區的小巷子裡。「 Sappho 」是其中最具代表性的 Jazz Bar，創立超過二十年，店內維持著昏暗的燈光和慵懶的沙發區，現場演奏的水準在本地樂手圈有口皆碑。這裡沒有華麗的裝潢，卻有最純粹的音樂靈魂。門票通常在 NT$200-400 元之間，有些時段免費入座但會建議低消一杯調酒。另一家值得一訪的是「 Brown Sugar 」，同樣以 Jazz 和靈魂樂為主軸，週末常有 Jam Session，意思是觀眾可以上臺和樂手一起即興演出——如果你本身會演奏任何樂器，這裡可能是你在臺北最難得的表演機會。\n\n**文創園區的戶外音樂場景**\n\n不想進室內？華山文創園區和大稻埕碼頭的戶外演出是另一種風景。華山的 Legacy mini 經常舉辦各種主題音樂活動，從獨立音樂到電子音樂派對都有，票價依陣容不同約 NT$300-800 元。大稻埕碼頭每逢週五週六則有河岸音樂會，主要是免費或自由捐助的形式，夕陽搭配現場音樂，是旅途中難得的愜意體驗。松山文創園區的戶外廣場也偶爾會有音樂市集型別的活動，適合把看錶演和逛文創小店結合在一起。\n\n**表演藝術的多元可能**\n\n臺北的 Live 場景不只有音樂。喜歡脫口秀或相聲的話，「【PLAY 嘻哈】【空】悲情城市」這型別的劇場演出近幾年在水源劇場和華山烏梅劇院經常可見。相較於純音樂的 Live House，這類表演更注重語言藝術和觀眾互動，票價通常在 NT$500-1,200 元之間。對外國遊客來說，這也是一個體驗臺灣本土喜劇文化的好機會。\n\n**實用資訊**\n\n關於交通，以上提到的場地大多集中在捷運沿線：高空酒吧主要在信義區（捷運臺北 101/世貿站），Jazz 酒吧多分佈在民生社群（捷運中山國中或松山機場站）和東區（忠孝敦化站），華山文創園區則在忠孝新生站步行五分鐘內可達。大稻埕需要搭乘淡水信義線至大橋頭站步行約十分鐘。\n\n票價方面，傳統 Live House 的演出票價約 NT$300-800 元，Jazz 酒吧多為低消制（NT$300-500 元），高空酒吧的表演則視餐飲消費而定。高雄同級場館票價通常在 NT$300-800 元區間，臺北整體略高，但選擇也更加豐富。\n\n**小提示**\n\n臺北的 Live 表演很多是臨時性或陣容變動快的，建議出發前先在各大場館的 Instagram 或 Accupass 活動平臺確認當天節目。另外，許多 Jazz 酒吧和小型 Live House 不接受事先預約，採取現場排隊制，週末建議提早到場。穿著方面，高空酒吧有 Dress Code（通常要求smart casual），一般 Live House 和 Jazz 酒吧則穿著舒適即可。如果你對某個特定樂團或歌手有興趣，追蹤場館的粉絲專頁是掌握第一手資訊的最佳方式。",
  "license": "CC BY 4.0"
}