{
  "title": "阿里山夜晚體驗：高山上的音樂與文化日常",
  "slug": "taiwan-entertainment-live-houses-alishan-阿里山夜晚體驗-高山上的音樂與文化日常-753571",
  "industry": "entertainment",
  "category": "live-houses",
  "area": "alishan",
  "url": "https://taiwan-encyclopedia.vercel.app/articles/taiwan-entertainment-live-houses-alishan-阿里山夜晚體驗-高山上的音樂與文化日常-753571.html",
  "published": "2026-06-14",
  "quality_score": 6.5,
  "word_count": 1728,
  "tags": [
    "阿里山",
    "夜晚體驗",
    "高山旅遊",
    "阿里山烏龍茶",
    "觀星"
  ],
  "content": "說到阿里山，大部分人的第一印象可能是日出、雲海、森林小火車這些經典風景。但你知道嗎？當太陽西沉、遊客散去之後，這座海拔2000公尺的高山茶鄉其實藏著一股不為人知的文化能量——沒有霓虹閃爍的Live House，卻有著屬於高山夜晚的獨特音樂風景。\n\n阿里山的夜晚體驗，其實是近年來深度旅遊興起後才逐漸被發掘的領域。這裡沒有城市裡的熱鬧夜店文化，但不代表沒有「夜間活動」可以探索。對我來說，阿里山的夜，是屬於茶農作息與自然聲響的夜。\n\n\n## 高山上的音樂日常：不是Live House的音樂體驗\n\n首先必須說清楚：阿里山區域內並沒有傳統定義的Live House店家。如果你期待走進一個有舞臺、有音響、有調酒師傅的音樂展演空間，可能會失望而歸。這裡的「夜晚音樂」，是另一種形態的存在。\n\n阿里山茶區的夜晚，常有茶農在製茶廠裡播放音樂。阿里山高山茶的製作過程中，萎凋、攪拌、烘乾等步驟需要耗時數十小時，茶農們常邊工作邊聽音樂提神。這種「製茶場景中的背景音樂」，某種程度上就是阿里山版的「現場音樂」——不是表演給觀眾看的，而是勞動生活的一部分。\n\n此外，阿里山森林遊樂區內的沼平公園廣場，在夏季偶爾會舉辦小型社群活動或音樂交流。這類活動通常不是商業性質的演出，而是地方居民或志工組織的自發性表演，充滿濃濃的人情味。如果你運氣好遇到，別忘了給這些熱情的演出者一些掌聲。\n\n\n## 推薦體驗：阿里山的夜這樣玩\n\n既然來到阿里山，不妨用不同的視角感受高山的夜晚。以下是我的私房推薦：\n\n### 1. 夜晚品茶體驗\n阿里山的夜晚氣溫驟降（冬季可能降至5°C以下），走進一家高山茶行，點一壺阿里山烏龍茶暖暖身子，是最道地的夜遊方式。茶農通常會在晚上進行茶葉烘焙，這時候走訪茶廠，常常能聞到陣陣茶香。阿里山烏龍茶的特色是花香與乳香交織，入口回甘，夜晚品茶特別能感受到茶湯的層次變化。\n\n### 2. 觀星與夜觀\n阿里山海拔高、空氣清淨，是臺灣重要的觀星地點之一。沒有光害的影響，天氣晴朗時可以清楚看見銀河。許多民宿會舉辦夜間觀星活動，由專人帶領辨識星座。這不是Live House，但那份抬頭看見滿天星斗的震撼，一點也不輸給任何一場演唱會。\n\n### 3. 凌晨看日出（傳統但經典）\n阿里山最著名的「夜晚活動」其實是凌晨的日出。為了搶看日出，遊客通常凌晨三、四點就得起床，搭乘森林小火車前往祝山車站。這是一種獨特的「夜遊」——摸黑出發，在黑暗中等待，當第一道陽光突破地平線的那一刻，整個觀景臺會響起歡呼與掌聲。這樣的「現場體驗」，是阿里山專屬的活動。\n\n### 4. 民宿音樂交流\n部分阿里山特色民宿的老闆本身是音樂愛好者，會在公共空間播放黑膠唱片或舉辦小型音樂分享。這類體驗充滿隨機性，通常需要事先與民宿溝通或運氣夠好才能遇到。這種「主人與客人的音樂交流」，是家庭式旅宿特有的溫暖。\n\n\n## 實用資訊\n\n### 交通方式\n從嘉義市區開車或搭乘客運（嘉義縣公車）前往阿里山，車程約2小時。山區道路蜿蜒，自駕需注意山路駕駛安全。也可搭乘阿里山森林小火車從嘉義站出發，感受復古的鐵路風情。\n\n### 住宿費用\n阿里山民宿雙人房淡季約 NT$1,500-3,000，旺季（櫻花季、連續假期）可能漲至 NT$3,000-5,000。部分優質茶民宿體驗可能更高。建議提早預訂。\n\n### 最佳季節\n阿里山四季皆有不同的魅力：3-4月櫻花季人潮最多、夏季涼爽適合避暑、秋冬雲海季景緻夢幻。但如果想體驗「夜晚的靜謐」，建議選擇非假日的平日造訪，遊客散去後的阿里山，有著難得的寧靜美感。\n\n\n## 旅遊小提示\n\n阿里山的夜晚商家大多休息較早，大部分餐廳在晚上8點後就不太有營業。建議傍晚前先解決晚餐再上山。\n\n山區夜晚溫差大，即使是夏季也建議攜帶外套。冬季上山務必注意保暖，帶好暖暖包或備用衣物。\n\n最後，如果你真心追求「音樂展演」的體驗，阿里山區域確實無法滿足這個期待。建議將目標改為「高山的夜間文化體驗」——品茶、觀星、等待日出，這些才是阿里山夜晚的正確開啟方式。\n\n阿里山的夜，不是喧鬧的，而是靜謐的、有深度的。這裡沒有Live House，但有城市裡感受不到的高山氣息與自然聲響。",
  "license": "CC BY 4.0"
}