{
  "title": "九份玉石購物指南：山城礦業遺產與珍寶工藝的深度探索",
  "slug": "taiwan-shopping-jade-market-jiufen-九份玉石購物指南-山城礦業遺產與珍寶工藝的深度探索-6f0b52",
  "industry": "shopping",
  "category": "jade-market",
  "area": "jiufen",
  "url": "https://taiwan-encyclopedia.vercel.app/articles/taiwan-shopping-jade-market-jiufen-九份玉石購物指南-山城礦業遺產與珍寶工藝的深度探索-6f0b52.html",
  "published": "2026-06-06",
  "quality_score": 7.5,
  "word_count": 1794,
  "tags": [
    "九份玉石",
    "九份購物",
    "新北珠寶",
    "瑞芳礦區",
    "台灣玉"
  ],
  "content": "說起九份，多數人想到的是復古茶樓、芋圓甜品和霧濛濛的基山街。但很少人知道，這座小山城其實與臺灣珠寶玉石產業有著深厚的淵源——這裡曾是金瓜石金礦的核心產區，如今老街上仍藏著幾家由老礦工或珠寶世家經營的特色店鋪，賣的不只是觀光紀念品，而是真正有價值的玉石工藝品。\n\n九份的珠寶玉石店家分佈與一般連鎖珠寶行不同，它們不是集中在商場裡，而是散落在老街的巷弄與階梯間，需要慢慢逛、慢慢聊，才能發現好店。這種「礦脈式」的分佈，反而讓購物過程像是一場小型探險。\n\n**特色亮點**\n\n九份的玉石購物體驗有三大特色：\n\n第一，「礦區直營」的價格優勢。由於九份曾是世界金礦產地，部分店家與礦區有直接供應鏈關係，省去中間盤商的層層剝削，價格往往比都會區珠寶店來得實惠。\n\n第二，工藝品的生活化。不同於高檔珠寶行的精品導向，九份老街的玉石店更注重工藝品的日常實用性——玉鐲、茶具、擺件、小配件，價格帶落在數百元到數千元之間，送禮自用兩相宜。\n\n第三，店主的故事性。許多店家本身或其家族就是礦業從業人員或珠寶加工業者，願意分享九份的礦業歷史和辨別玉石的基礎知識，購物之餘還能聽一段「礦工變珠寶商」的真實人生。\n\n**推薦店家**\n\n推薦一：「瑞芳礦工玉坊」。這家店隱藏在基山街末端的一條小巷中，招牌不起眼，卻是許多內行人才知道的口袋名單。店主是第二代礦工子弟，店內主打來自花蓮的臺灣玉（又稱「豐田玉」）原石和簡單加工的吊墜、手環。臺灣玉的價格帶約在新臺幣300元至2,000元之間，是少見的「礦區直供」價格。店主的父親曾參與金瓜石礦坑工作，常被問起礦區往事，願意分享第一手的礦業回憶。\n\n推薦二：「山城琥珀屋」。九份老街靠近昇平戲院的位置，有一家專營琥珀和蜜蠟的特色小店。店主是嘉義阿里山的原住民，對琥珀的來源和等級有深入研究。店內的琥珀飾品價格約在新臺幣500元至8,000元不等，根據透明度、內含物和產地分級。店主強調，購買琥珀時「越透越值錢」，內含昆蟲或植物的「蟲珀」價格會顯著提升。這家店的特色是「先聊後買」——店主會先用15分鐘講解琥珀的形成原理和辨別方法，再讓顧客自行決定。\n\n推薦三：「貢寮石藝小舖」。這家店的位置在九份遊客中心旁的階梯下方，主打來自貢寮海岸的「海底石」工藝品——這是東北海岸特有的海岸石，經過海水長期沖刷後呈現獨特的灰白和淡綠色紋路。小件的話（如鑰匙圈、小擺件）價格在新臺幣200元至800元之間，大件（如書鎮、擺盤）則在1,500元至5,000元。這家店的特色是「客製化雕刻」，顧客可以選擇簡單的文字或圖案請店主現場雕刻。\n\n推薦四：「金瓜石礦石標本館」。嚴格來說這不是珠寶店，而是一家礦石標本和原石陳列館，位於金瓜石黃金博物園區附近的巷子裡。店內陳列著金瓜石礦區出產的各種礦石標本——包括含金石英、黃鐵礦、毒砂等喜歡礦石科學的人會很有興趣的標本。價格從新臺幣100元的小標本到數千元的大塊都有，適合帶回家當作礦業歷史的紀念。\n\n推薦五：「九份玉石批發工作室」。這家店位於老街外圍、靠近停車場的巷子裡，外觀類似一般民宅，沒有顯眼招牌，須由熟人帶路或電話預約。店主原本在臺北永和玉市經營批發，退休後回到九份老家做零售，主要供應中低價位的玉石配件（手珠、項鏈、手鐲），價格帶落在新臺幣200元至1,500元之間。這裡的議價空間比一般店面大，店主表示「批發出身的，習慣了」。\n\n**實用資訊**\n\n交通方面，可從臺北火車站搭乘臺鐵區間車至瑞芳車站（約35分鐘），轉乘公車或計程車至九份老街；自駕可將車停放在九份停車場（小型車收費每次新臺幣100元）。\n\n營業時間方面，九份老街店家多在上午10點至下午6點之間營業，部分店家有固定公休日，建議事先電話確認。\n\n最佳季節方面，九份的珠寶玉石購物全年皆宜，但建議避開連續假日的尖峰人潮，平日或下午3點過後逛老街，店家比較有時間詳細介紹。\n\n**旅遊小提示**\n\n購買玉石時，記住「一看二問三摸」的口決：先看光澤是否溫潤均勻，再問產地和等級，最後用手觸控感受質地是否細膩。九份老街的店家普遍願意讓顧客用手電筒照射檢視玉石，這是基本的權利，不需不好意思。\n\n此外，九份的玉石店家多為家族經營小店，較少使用電子支付，建議隨身攜帶適量現金。最後，別把九份的玉石購物想成「臺北玉市」的縮小版——這裡的價值在於「礦區故事」和「工藝體驗」，不是批發價差。",
  "license": "CC BY 4.0"
}