{
  "title": "九份玉石購物指南：山城裡的尋寶小旅行",
  "slug": "taiwan-shopping-jade-market-jiufen-九份玉石購物指南-山城裡的尋寶小旅行-6ea04a",
  "industry": "shopping",
  "category": "jade-market",
  "area": "jiufen",
  "url": "https://taiwan-encyclopedia.vercel.app/articles/taiwan-shopping-jade-market-jiufen-九份玉石購物指南-山城裡的尋寶小旅行-6ea04a.html",
  "published": "2026-07-16",
  "quality_score": 7.5,
  "word_count": 1385,
  "tags": [
    "九份玉石",
    "九份購物",
    "九份老街",
    "台灣礦石",
    "山城尋寶"
  ],
  "content": "很多人來九份只為了一碗芋圓和一張千與千尋的打卡照，卻不知道這座小山城裡，其實藏著幾間別有洞天的玉石小店。沒有傳統市場的喧鬧，這裡的玉石店家更像隱藏在巷弄間的驚喜，等著有緣人推門而入。\n\n九份的玉石店家並非集中在某一條街上，而是散落在老街周邊的分支巷弄裡。這種「尋寶探險」式的購物體驗，反而成為九份玉石的最大特色——你永遠不知道下一個轉角會遇見什麼。根據業界觀察，臺灣玉石市場近年來從傳統批發轉向體驗經濟，小型特色店鋪越來越受歡迎，而九份正完美契合這種趨勢。\n\n**第一家值得推薦的是「山城礦石屋」**。這間店位於基山街末端靠近阿妹茶樓的位置，店面不大，但櫥窗裡陳列著來自花蓮和臺東的各色玉石原石與成品。店主是位低調的老師傅，鮮少主動推銷，卻樂於和客人分享玉石的成因與鑑別知識。店內商品以吊墜、手串為主，價格區間落在新臺幣300至2,000元之間，是初次接觸玉石的旅客不錯的起點。\n\n**第二家是「瑞芳時光」**，藏身在豎崎路的一條支巷裡。這間店的風格與傳統玉石店截然不同，混合了復古裝潢與文創飾品，選品偏向年輕化設計。店內除了臺灣本土玉石，還引進了少見的國外礦石，如墨西哥藍珀、巴西紫水晶等。價格從500元起跳，最貴的收藏級作品可達上萬元。特別的是，這裡的玉石飾品大多經過設計師重新鑲嵌，呈現出與傳統玉石不同的時尚感，適合尋求獨特紀念品的年輕旅客。\n\n**第三家不能錯過的是「九份紀念品小鋪」**，雖然名字樸實，但老闆娘對玉石頗有研究。這間店的位置在輕便路附近，靠近昔日九份最大的昇平戲院。店內商品以小巧的隨身飾品為主，像是玉石耳環、戒指、胸針等，價格非常親民，大約落在150至800元之間。老闆娘說得一口好故事，會告訴你每塊玉石的產地和特色，這種「有溫度的購物體驗」正是大型市集無法比擬的。\n\n**第四家是「山海礦石」**，位於較少遊客到達的內九份溪地區。這間店的優勢在於價格實惠，選擇多元，特別是玉石原石的裸石，常吸引一些DIY愛好者前來挑選。店內也有提供簡單的客製化服務，像是將玉石重新穿繩或鑲嵌。價格範圍從200元的入門款到5,000元的中價位都有，彈性很大。\n\n最後一家是比較特別的「手作工坊」，沒有固定店名，位於阿妹茶樓旁的二樓。這裡不是傳統零售店，而是複合式空間，一樓是茶飲區，二樓展示著店主手作的玉石飾品。每件作品都是獨一無二的，價格根據設計複雜度從800元到3,000元不等。店主本身是珠寶設計師背景，作品融合了九份的山城意象，像是刻有山稜線的玉墜，或是融入雨季霧氣意象的透明玉飾，非常有紀念價值。\n\n**實用資訊方面**，九份的玉石店家大多沒有固定的公休日，但建議避開假日人潮最洶湧的時段（上午10點至下午2點），傍晚後造訪反而更能悠閒地挑選。由於九份老街是坡道為主，建議穿著舒適的鞋子前往。這些店家普遍接受現金交易，少部分支援行動支付。\n\n**交通資訊**：從臺北車站搭乘臺鐵至瑞芳站（約35分鐘），轉乘公車或計程車即可抵達九份老街。自駕的話，九份有公有停車場但車位有限，例假日常一位難求。\n\n**小提示**：九份的玉石店家並不像花蓮或臺中的玉石市場那樣規模化，每間店的存貨量有限，難得遇到心動的商品建議當場決定。此外，九份山坡濕滑，雨季（10月至12月）前往時請留意路面安全。購買玉石時可以多和店主聊聊，很多有趣的礦區故事往往比商品本身更吸引人。",
  "license": "CC BY 4.0"
}