{
  "title": "臺南Live House不完全指南：古都巷弄裡的音樂秘密基地",
  "slug": "taiwan-entertainment-live-houses-tainan-臺南live-house不完全指南-古都巷弄裡的音樂秘密基地-eff06b",
  "industry": "entertainment",
  "category": "live-houses",
  "area": "tainan",
  "url": "https://taiwan-encyclopedia.vercel.app/articles/taiwan-entertainment-live-houses-tainan-臺南live-house不完全指南-古都巷弄裡的音樂秘密基地-eff06b.html",
  "published": "2026-07-16",
  "quality_score": 6.5,
  "word_count": 1527,
  "tags": [
    "台南 Live House",
    "台南音樂展演",
    "台南夜生活",
    "台南景點推薦",
    "古都音樂"
  ],
  "content": "說到臺南，多數人先想到的是牛肉湯、蝦捲和古蹟，但其實這座老城市近年悄悄長出了好幾間風格鮮明的Live House。它們不像臺北那樣熱鬧擁擠，也不像臺中那樣百花齊放，卻有種難得的從容感——在百年老屋裡聽團演出，喝著本土啤酒，看著舞臺上投射的歌詞，這就是臺南特有的「古都音樂夜」。\n\n**臺南Live House的與眾不同**\n\n臺南的Live House有個顯著特色：很多空間本身就是老屋再生。經營者和樂團似乎有默契，不追求華麗裝置，而是把力氣花在「氣氛」上。你可能會在昭和時代的洋樓裡聽搖滾，或是在老醫院的候診區看獨立樂團演出。這種「以老屋為容器」的形態，讓看錶演這件事多了時光層次感，也吸引了不少文青族群和觀光客專程朝聖。\n\n票價方面，臺南的Live House相對親民，大型演出票價約在250-600元之間，小型不插電演出或開放 mic 場次甚至免費或只收場地費。這個價格帶對學生和小資族相當友善，也難怪有不少中南部的樂迷專程南下「跑場」。\n\n**三傢俬心推薦的臺南Live House**\n\n**MUSE 音樂展演空間**\n位於中西區的MUSE，是臺南少數具有專業燈光音響裝置的展演空間。雖然藏在巷子裡，但室內空間寬敞，舞臺和觀眾區的動線設計得當，即使站在最後一排也能清楚看見演出者。這裡的曲目取向較廣，從主流搖滾到獨立民謠都有機會聽到，也是許多中部以南樂團南下巡演的固定據點。MUSE每週固定有數場Live演出，偶爾還會舉辦主題音樂節或 DJ 派對，是想要「認真聽一場表演」的首選。\n\n**故障島 Fault Island**\n這間店名本身就很有態度——它位於東區的巷弄民宅內，外觀低調到你路過可能會錯過。推開門後是另一個世界：小舞臺、斑駁磚牆、老式木窗改造的裝飾，氛圍非常「地下」。故障島的演出以另類搖滾、龐克、後搖滾為主，偶爾也會有實驗電子和 DJ セット。這裡的觀眾族群相對年輕，演出時常出現「人貼人」的熱烈場面，舞臺魅力和互動感是最大亮點。若你厭倦了連鎖展演空間的制式感，這裡的「不完美」正是它的魅力所在。\n\n**十八號書局**\n十八號書局並不是傳統意義的Live House，它原本是間老書局，後來轉型為複合式空間，白天才賣書，晚上則變身為小型音樂場地。這裡的舞臺非常迷你，最多隻容得下三到四位演出者，觀眾圍坐在四周，距離近到幾乎能聽見演出者的呼吸聲。選曲偏向抒情、民謠、詩歌朗讀等「慢節奏」型別，非常適合想要放鬆、聊天的夜晚。這裡的低消門檻也很佛心，一杯飲料就能坐整晚，是體驗臺南「慢生活」音樂文化的絕佳選擇。\n\n**實用資訊**\n\n**交通方式**：臺南主要Live House集中在中西區和東區，建議搭乘臺鐵或高鐵至臺南站後，轉乘市區公車或租借 YouBike。市區範圍不大，多數場地步行即可抵達，但晚間演出結束後建議叫計程車，安全為上。\n\n**費用參考**：門票150-600元不等，視演出規模和陣容而定；場地低消約100-200元，相當於一杯調酒或無酒精飲料。\n\n**營業時間**：Live House通常在晚上七點後開門，演出大多從八點半到十點半之間進行，週五週六最熱鬧，週日則常有午間或傍晚的輕鬆演出。\n\n**旅遊小提示**\n\n第一，臺南的Live House普遍規模較小，座位有限，熱門演出建議提早到場，尤其是週六晚間的黃金時段。第二，很多場地是「站票制」，穿舒適的鞋子才能撐完整場。第三，古都的夜生活節奏偏慢，不用趕著衝下一個行程，好好享受當下的音樂最重要。最後，也是最重要的一點——別只把Live House當背景，開啟手機錄音功能不如開啟眼睛和耳朵，用心感受臺南夜晚的音樂溫度，這才是這座城市最珍貴的「隱藏景點」。",
  "license": "CC BY 4.0"
}