{
  "title": "花蓮夜泡溫泉美食：暮色山嵐中的暖胃提案",
  "slug": "taiwan-dining-hot-springs-dining-hualien-花蓮夜泡溫泉美食-暮色山嵐中的暖胃提案-b77710",
  "industry": "dining",
  "category": "hot-springs-dining",
  "area": "hualien",
  "url": "https://taiwan-encyclopedia.vercel.app/articles/taiwan-dining-hot-springs-dining-hualien-花蓮夜泡溫泉美食-暮色山嵐中的暖胃提案-b77710.html",
  "published": "2026-06-22",
  "quality_score": 7.5,
  "word_count": 1253,
  "tags": [
    "花蓮溫泉",
    "溫泉美食",
    "瑞穗溫泉",
    "花蓮夜景",
    "花東溫泉"
  ],
  "content": "多數人來花蓮泡溫泉，選擇的是白天入園、傍晚離開的標準行程。但真正的內行人知道，花蓮溫泉區的夜色才是精髓——白天遊客散去後，餐廳不用排隊、露天池只剩山風與星空，而山區夜晚的涼意，正好讓人胃口大開。\n\n瑞穗溫泉區、安通溫泉區沿著臺鐵花東線分佈，這條鐵道是花蓮溫泉美食的最大資產。不用開車就能從花蓮市區直達瑞穗車站，再轉乘當地接駁或步行至溫泉餐廳，對於不自駕的旅行者相當友善。\n\n**夜晚溫泉餐廳的三大特色**\n\n首先是人潮差異。花蓮溫泉區的餐廳與溫泉池多數下午四點過後就解除人潮高峰，晚間用餐不僅不需要提前預約，有些甚至能享有包場般的安靜。其次是溫度對比。山區夜晚氣溫驟降至15-18度，浸泡碳酸氫鈉泉後毛孔張開，此時吃一碗熱湯或火鍋，那種由內而外的暖意是白天體驗不到的。第三是光影氛圍。少了觀光人潮，餐廳的照明回歸溫暖的黃光，搭配山間夜色，視覺體驗完全不同於城市的夜景餐廳。\n\n**三家推薦店家**\n\n「松盧餐廳」位於瑞穗溫泉路上，是當地三十年資深老店，招牌白切雞與苦瓜湯是經典。晚餐時段從下午五點開始，一路營業到晚上九點，人潮比午餐時段少上許多。推薦點一份雞油拌飯（NT$80）配苦瓜排骨湯（NT$150），兩人消費約NT$350-450。這裡的優勢是上菜速度快、價格實惠，適合趕在泡湯前快速用餐。\n\n「山間五月」則走的是精緻路線，位於安通溫泉區的半山腰，必須打電話預約才接待。餐廳只有六張桌子，主打在地食材的創意料理，烤香魚（NT$280）和山藥時蔬（NT$180）是招牌。整體消費落在NT$500-800之間，屬於慶祝性質的晚餐選擇。老闆娘會根據當天採買的食材推薦菜品，這種不固定選單的做法反而讓人期待。\n\n如果偏好平價選擇，「祥安自助餐」在瑞穗車站步行範圍內，是當地人解決三餐的日常小店。均一價NT$100的自助取餐，想吃多少夾多少，滷肉飯、炒青菜、湯品無限供應。這裡不適合追求氣氛，但對於預算有限的揹包客來說，一百元就能吃飽的CP值無可挑剔。營業時間從上午六點到晚上八點，泡完溫泉回來順路吃個消夜剛剛好。\n\n**實用資訊**\n\n交通方面，從花蓮市區搭乘臺鐵區間車至瑞穗站（約1.5小時），票價約NT$156；或至安通站（約2小時），票價約NT$206。瑞穗火車站前有計程車可包車至溫泉區，單程約NT$200-300；若預算有限，可選擇步行，瑞穗溫泉路沿線約2公里，邊走邊欣賞田野風光。\n\n溫泉費用方面，瑞穗溫泉區的公共浴池一次約NT$80-150，個人湯屋約NT$200-400；安通溫泉區相對便宜，公共池約NT$50-100。餐廳消費則落在NT$100-800之間，端看選擇的店家與菜色。\n\n營業時間差異大，部分餐廳過了晚上八點就結束營業，建議抵達前先電話確認。\n\n**旅遊小提示**\n\n花蓮山區日夜溫差大，夏天夜晚仍需帶件薄外套，冬天則建議洋蔥式穿法。溫泉餐廳多數接受現金交易，行動支付普及度不及臺北，務必準備足夠現金。如果計畫泡完湯直接用餐，建議先打電話預約餐廳座位，否則可能遇到客滿的情況。",
  "license": "CC BY 4.0"
}