{
  "title": "日月潭晨間寺廟巡禮：日出時分的祈福體驗與湖畔靜謐",
  "slug": "taiwan-tourism-temples-sun-moon-lake-日月潭晨間寺廟巡禮-日出時分的祈福體驗與湖畔靜謐-b07ba1",
  "industry": "tourism",
  "category": "temples",
  "area": "sun-moon-lake",
  "url": "https://taiwan-encyclopedia.vercel.app/articles/taiwan-tourism-temples-sun-moon-lake-日月潭晨間寺廟巡禮-日出時分的祈福體驗與湖畔靜謐-b07ba1.html",
  "published": "2026-07-10",
  "quality_score": 6.5,
  "word_count": 2225,
  "tags": [
    "日月潭寺廟",
    "清晨祈福",
    "日出景點",
    "台灣宗教旅遊",
    "日月潭自由行"
  ],
  "content": "說到日月潭的寺廟，多數遊客想到的是白天參拜、傍晚離開的標準行程。但真正懂行的人知道，清晨五點半起床，趕在日出前抵達湖畔寺廟，那種霧氣繚繞、湖面金光逐漸散開的時刻，才是日月潭寺廟最動人的模樣。\n\n這篇文章不寫傳統的寺廟巡禮，而是帶你用「清晨視角」重新認識日月潭的信仰地景。從文武廟的日出觀景臺，到玄奘寺的晨鐘暮鼓，再到水社觀音的便利參拜，每一座廟都有它最適合的到訪時段。\n\n---\n\n## 特色亮點\n\n日月潭周邊的寺廟與一般山區廟宇最大的不同，在於它們幾乎都「面湖」。這意味著清晨參拜時，你不只是祈福，更能同時享受湖光山色。根據觀光局統計，日月潭年度遊客量超過八百萬人次，但清晨六點到八點的「晨間時段」，遊客量僅佔全天的8%左右，意味著你能在相對安靜的環境中，體驗在地人真正的日常。\n\n更重要的是，清晨的日月潭有著難得的「霧氣景觀」。每到清晨，湖面會升起薄霧，寺廟的屋脊在霧中若隱若現，彷彿時間都慢了下來。這種景觀是下午遊客高峰期完全無法感受到的。\n\n---\n\n## 推薦地點\n\n### 日月潭文武廟\n\n如果只能選一個地方看日月潭日出，文武廟是首選。這裡的聖關公祠廣場是著名的日出觀景點，農曆新年期間甚至會有凌晨四點就來排隊的遊客，只為搶佔第一排位置。\n\n文武廟的特色在於它的「雙重身份」：既是傳統道教廟宇，也是俯瞰日月潭的最佳制高點。寺廟建築融合了閩南與客家風格，最值得注意的不是主殿，而是後方的觀景平臺——從這裡看出去的湖面，會隨著太陽升起呈現從深紫到金黃的漸層變化。\n\n建議到訪時間：清晨五點半至六點之間抵達，先參拜祈福，再等待日出。\n\n### 玄奘寺\n\n從文武廟往下走，玄奘寺藏在中興停車場附近的山坡上，這裡是日月潭最深幽的寺廟。不同於一般香火鼎盛的廟宇，玄奘寺因為供奉唐代高僧玄奘法師而增添了一層文化厚度，環境清淨許多。\n\n清晨的玄奘寺幾乎沒有遊客，你可以聽見鳥鳴、風聲，以及遠處湖面的水波。寺內環境維護得很好，殿堂莊嚴但不冰冷。這裡適合想要「沉靜心靈」的旅人——不是為了求神問卜，而是為了一份難得的安靜。\n\n玄奘寺下方不遠處就是著名的「向山腳踏車道」，如果你有計畫騎單車環湖，清晨參拜後正好可以開始一日騎行。\n\n### 龍鳳宮（月下老人祠）\n\n龍鳳宮最特別的是月下老人祠，這在臺灣並不常見。傳說這裡的月下老人特別靈驗，年輕情侶和求姻緣的遊客特別多，但也因為這個「靈驗」標籤，讓龍鳳宮白天人潮絡繹不絕。\n\n但清晨的龍鳳宮是另一番景象。建議清晨六點左右到訪，這時廟公剛開門，燭火才點上，你可以靜靜參拜，感受那份神聖感。龍鳳宮就緊鄰水社碼頭，參拜完還可以順便在湖畔散步，等待湖面日出。\n\n如果你是「便利性優先」的旅人，龍鳳宮是最佳選擇——距離水社遊客中心僅三分鐘路程，周邊早餐店林立，參拜完直接吃早餐繼續行程。\n\n### 水社觀音\n\n水社觀音是日月潭最大規模的觀音廟，建築規模和香火鼎盛程度都是周邊之最。不同於其他寺廟需要開車或騎車前往，水社觀音就在水社遊客中心旁邊，步行即可到達，對開車族或搭客運的遊客非常友善。\n\n清晨的水社觀音有一個隱藏版亮點：廟後方的步道。這條步道人跡罕至，沿途林蔭茂密，走到盡頭可以俯瞰日月潭全景，卻幾乎沒有遊客知道。這個「秘境」資訊很少出現在旅遊書上，卻是在地人清晨運動的秘密路線。\n\n---\n\n## 實用資訊\n\n### 交通方式\n\n開車：從國道六號愛蘭交流道下來，沿臺21線往日月潭方向，約三十分鐘可抵達水社地區。清晨路況良好，停車位充足。\n\n大眾交通：搭乘臺灣好行日月潭線，在「水社」或「文武廟」站下興。臺灣好行班次密集，單程票價 NT$190-250，視上車地點而定。建議提早在前一晚預訂，以免向隅。\n\n船運：如果你想體驗「水路」參拜，可以搭乘最早的遊艇，從水社碼頭出發，沿湖面觀賞日出，再於玄奘寺碼頭上岸參拜。首航班次約清晨六點開航，單程票價約 NT$300。\n\n### 費用\n\n所有寺廟均免費參拜。部分寺廟提供點香服務，隨喜功德 NT$50-100。\n\n### 營業時間\n\n各寺廟約清晨六點開門，晚間六點關門。龍鳳宮因為緊鄰碼頭，營業時間較早，清晨五點即有人留守。\n\n---\n\n## 旅遊小提示\n\n1. **日出時間查詢**：臺灣的日出時間隨季節變化極大，冬季（11-2月）約六點半天亮，夏季（五至八月）則提前到五點左右。建議出發前一晚先查詢當日日出時間，提前三十分鐘到場卡位。\n\n2. **穿著建議**：清晨湖邊氣溫較低，即使是夏天也建議帶件薄外套。冬季（五至十五度）務必準備羽絨外套。\n\n3. **在地早餐**：水社周邊有幾家在地早餐店，例如「日月潭早餐」提供在地切仔麵和豆漿，價格實惠（一份套餐 NT$60-80），吃完再開始參拜剛剛好。\n\n4. **避開人潮的黃金法則**：只要掌握「清晨六點到八點」這個時段，就能享受日月潭寺廟難得的寧靜。這個時段不只適用於寺廟，也適用於環湖腳踏車道和遊船——相同的風景，不同的體驗。\n\n5. **尊重在地文化**：日月潭的邵族是臺灣原住民中人口最少的一支，近年邵族文化工作者多次呼籲遊客尊重當地生活，不要把寺廟參拜變成「到此一遊」的打卡行程。請保持安靜、不要使用閃光燈拍攝神像，這是最基本的尊重。\n\n清晨的日月潭寺廟，沒有下午的喧囂，卻有著專屬於這片湖泊的靜謐與神聖。如果你願意稍稍犧牲一點睡眠，收穫的會是一個完全不同版本的日月潭——一個只屬於早起旅人的秘密風景。",
  "license": "CC BY 4.0"
}