{
  "title": "臺中音樂地圖：從街頭到地下——我的私房Live House口袋名單",
  "slug": "taiwan-entertainment-live-houses-taichung-臺中音樂地圖-從街頭到地下-我的私房live-house口袋名單-36b7f6",
  "industry": "entertainment",
  "category": "live-houses",
  "area": "taichung",
  "url": "https://taiwan-encyclopedia.vercel.app/articles/taiwan-entertainment-live-houses-taichung-臺中音樂地圖-從街頭到地下-我的私房live-house口袋名單-36b7f6.html",
  "published": "2026-07-10",
  "quality_score": 6.5,
  "word_count": 1976,
  "tags": [
    "台中",
    "Live House",
    "現場音樂",
    "音樂展演",
    "夜生活"
  ],
  "content": "說到臺中的音樂場景，很多人第一個想到的是逢甲夜市的熱鬧，或是草悟道的文創氣息。但如果你想聽真正的現場音樂，想感受那種觀眾和樂手近距離互動的熱度，Live House絕對是正解。這篇文章不談那些你需要「辨識真假」的商業陷阱，直接分享我口袋裡的幾家真材實料、音樂品質穩定的據點。\n\n**臺中Live House的獨特魅力**\n\n臺中的Live House和臺北、高雄不太一樣。這裡的場地規模普遍偏小，但氣氛特別親密——你可能站在離主唱不到兩公尺的距離，聽他講述那首歌背後的故事。這種「零距離」的體驗，是大型演唱會給不了的。\n\n近年臺中出現了不少複合式經營的音樂空間，它們結合咖啡廳、酒吧，甚至選物店，讓你可以先吃點東西、喝一杯，再慢慢進入音樂世界。這種「從晚餐一路聽到深夜」的悠閒節奏，意外地很符合臺中這座城市的生活步調。\n\n**我的私房推薦名單**\n\n**1. 浮現音樂展演空間**\n這家位於逢甲商圈附近的場地，是我最常去的live house之一。空間不大，大概只能容納七八十人，但正因為這樣，觀眾和樂手的距離超近。浮現的舞臺高度設計得剛剛好，不會有那種「被隔離」的感覺。\n\n這裡的音樂風格比較多元，另類搖滾、獨立民謠、後搖滾都有機會聽到。偶爾還會邀請國外的小型樂團來演出，票價通常在NT$300-600之間，算是非常親民的價位。場地旁邊就是停車場，交通也算方便。\n\n**2. 玩麻吉 Live House**\n如果你是那種喜歡「驚喜感」的聽眾，玩麻吉絕對不會讓你失望。這家場地沒有固定的演出 schedule，很多時候是臨時宣佈的即興演出或開放 mic 夜。你永遠不知道今晚會遇到什麼樣的音樂人，這種未知感反而讓每次造訪都像開獎。\n\n場地位於忠孝路夜市附近，空間偏暗，燈光氣氛做得很好，適合想要「放鬆喝酒、隨便聽點什麼」的夜晚。低消大約NT$200-300，可以換一杯啤酒或軟性飲料，在臺中這種價位算是佛心。\n\n**3. 洞穴 The Cave**\n聽名字就知道這裡不一樣——洞穴的空間真的有種「地下」的感覺，磚牆、昏暗的燈光、略帶粗獷的裝潢，氣氛非常適合聽重金屬或另類搖滾。\n\n這裡的觀眾年齡層普遍稍長一點，比較多是玩音樂的人或是重度樂迷。如果你對極端音樂有興趣，洞穴是臺中少數能穩定聽到金屬、朋克、噪音這類曲風的場地。演出票價浮動較大，視演出者而定，約NT$250-800。\n\n**4. 呼乾啦音樂bar**\n這是一家結合酒吧的Live House，位於SOGO商圈的巷子裡，交通超級方便。空間設計很有巧思，前面是酒吧區，後面是小舞臺，晚上九點過後開始有現場演出。\n\n呼乾啦的特色是「音樂種類不受限」——今晚可能是爵士三重奏，明晚可能就是流行鋼琴彈唱。對我來說，這裡最適合那種「想找地方坐著喝東西、順便聽點音樂」的夜晚，不會太正式，但又不會隨便。消費約 NT$150-400 的酒水錢，就可以待整個晚上。\n\n**5. 岔嗆音樂展演空間**\n最後一家要推薦的是岔嗆，這是臺中比較新的Live House之一，裝置和音效都處理得很好。空間比前面幾家稍大，約可容納一百人左右，視線不受限，音效也很專業。\n\n岔嗆經常舉辦主題之夜或是特定音樂型別的專場，如果你對華語獨立音樂有興趣，這裡的演出質量很不錯。票價區間約 NT$350-700，偶爾會有早鳥優惠，可以追蹤他們的社群媒體掌握資訊。\n\n**實用資訊**\n\n臺中的Live House主要分佈在逢甲、忠孝路和SOGO這三個商圈附近。大部分沒有自己的停車場，但因為都在市區，搭公車或騎YouBike都很方便。如果開車，附近都有收費停車場，計算下來每小時 NT$20-40。\n\n營業時間方面，臺中的Live House通常傍晚開始營業，高峰時段是晚上九點到十二點。建議提前到場，尤其是熱門演出，否則可能會遇到額滿的情況。部分場地需要提前購票，可以在Accupass或KKTIX上查詢。\n\n平均消費大約 NT$300-800，涵蓋門票和基本飲品，這個價位在臺灣的Live House市場中算是中等區間。\n\n**旅遊小提示**\n\n來臺中聽Live House，建議把行程排在傍晚。先去逢甲或一中街吃個晚餐，當作暖場墊墊胃，再慢慢散步到Live House。臺中的夜晚比臺北涼爽，走在路上很舒服。\n\n如果你對特定音樂型別有偏好，出發前先查一下當天的演出陣容，或者直接打電話問場地當晚的風格。臺中Live House的工作人員普遍很熱情，直接問他們「今晚有什麼推薦的」通常會得到很真誠的回答。\n\n最後提醒一下，大部分Live House都有年齡限制，雖然現在很多場地已經放寬到18歲，但最好還是先確認一下，以免到了現場被擋下來破壞興致。還有，別忘了帶點現金——不是每家都支援電子支付，但買酒的時候現金還是比較方便。",
  "license": "CC BY 4.0"
}