{
  "title": "臺北時光騎旅：踩踏百年城市紋理的歷史探索",
  "slug": "taiwan-tourism-cycling-routes-taipei-臺北時光騎旅-踩踏百年城市紋理的歷史探索-430ed2",
  "industry": "tourism",
  "category": "cycling-routes",
  "area": "taipei",
  "url": "https://taiwan-encyclopedia.vercel.app/articles/taiwan-tourism-cycling-routes-taipei-臺北時光騎旅-踩踏百年城市紋理的歷史探索-430ed2.html",
  "published": "2026-03-29",
  "quality_score": 6.5,
  "word_count": 1743,
  "tags": [
    "台北單車",
    "歷史文化",
    "老街探索",
    "日治建築",
    "大稻埕"
  ],
  "content": "當多數人把臺北單車路線框在河濱休閒或美食巡禮時，你有沒有想過，這座城市其實是一本立體的歷史書？從清代的河港商業、日治時代的都市計畫，到戰後的眷村文化，每個時代都在街道上留下印記。騎著單車穿梭其間，你不只是在運動，而是在閱讀一座城市的身世。\n\n作為長期研究臺灣老街文化的人，我發現臺北最迷人的騎行體驗，不在那些熱門景點，而在那些還保有歷史溫度的街廓。這裡的每塊磚、每道牆，都能訴說不同時代的故事。\n\n## 三個時代，三種騎行體驗\n\n臺北的歷史文化騎行，可以按時代分為三個層次。清代的大稻埕展現河港商業文明，騎在迪化街上你會感受到百年前茶商的忙碌；日治時代的中山北路一帶，寬敞的林蔭大道展現殖民政府的都市美學；戰後的眷村聚落雖多已改建，但在四四南村、建國南路一帶仍能捕捉到那個時代的生活痕跡。\n\n重點不是把這些地方當景點打卡，而是理解每個區域背後的歷史邏輯。為什麼迪化街的建築都是長條型？為什麼中山北路特別寬？為什麼某些街廓的房子特別密集？騎車的慢速度，正好讓你有時間觀察這些細節。\n\n## 推薦文化探索路線\n\n**大稻埕歷史街區**\n從迪化街出發，這裡儲存了臺北最完整的清代和日治商業建築群。南京西路到民生西路這一段，巴洛克式立面和傳統閩南街屋並存，每棟建築都有自己的故事。特別推薦騎到永樂市場周邊，那裡有最道地的布行文化，很多店家還在使用日治時代的木製櫃臺。騎行時注意建築二樓的裝飾細節，那是當年商人財力的展現。\n\n**中山北路官邸文化帶**\n從圓山到民權東路，這條日治時代規劃的「敕使街道」至今仍保持寬敞的林蔭風貌。沿途的領事館、官邸建築散佈在巷弄間，騎車穿梭比開車更容易發現。特別是中山北路二段的巷內，還能找到幾棟日式木造建築，雖然已改為咖啡廳或民宿，但建築本體儲存良好。這區域的騎行重點是感受日治時代的都市規劃理念。\n\n**剝皮寮歷史街廓**\n萬華剝皮寮是臺北少數完整保留的清代街區，紅磚建築和石板街道很適合慢速騎行。從老松國小騎到廣州街，整個街區像一座露天博物館。這裡的建築風格混雜了閩南、日式和現代元素，反映了臺北城市發展的複雜性。騎行時可以停下來看看店家門楣上的書法字號，那些都是真正的歷史痕跡。\n\n**北門城區文化圈**\n從臺北車站騎到北門，再延伸到撫臺街洋樓一帶，這裡是臺北城從古到今的核心。北門是唯一保留原貌的清代城門，周邊的鐵道部、郵政博物館都是日治建築精品。騎行路線建議從忠孝西路出發，繞行北門廣場，再轉入博愛路看撫臺街洋樓。這條路線短但資訊密度高，每個轉彎都是不同的歷史場景。\n\n**艋舺龍山寺周邊老街**\n龍山寺不只是宗教勝地，周邊的西昌街、華西街保留了大量戰後初期的街屋形態。騎車穿梭在這些窄巷中，你會發現很多傳統行業還在經營：中藥房、金紙店、神像雕刻店。這裡的騎行體驗比較原始，沒有太多觀光包裝，卻最能感受到老臺北的生活質感。建議傍晚時分前往，當地人下班回家的氛圍最濃厚。\n\n## 實用騎行資訊\n\n**租車選擇**\nYouBike在各歷史街區都有站點，30分鐘內NT$10，超時每30分鐘NT$15。建議使用悠遊卡或電子支付，比較方便。如果要深度探索，考慮在迪化街或西門町的腳踏車行租日車，一天約NT$200-400，車況較好且有變速功能。\n\n**最佳探索時間**\n平日上午9-11點是最理想的騎行時段，人車較少，店家剛開始營業，最適合觀察建築和街道細節。週末建議避開上午10點後，特別是迪化街會有很多遊覽車。夏季建議早上7-9點出發，避開正午高溫。\n\n**停車與安全**\n歷史街區多為窄巷，騎行時請減速並留意行人。迪化街、剝皮寮都有機車停車格可暫停腳踏車，但請注意不要妨礙商家營業。中山北路沿線有較多人行道，停車相對容易。\n\n## 文化探索小貼士\n\n記住，你騎的不只是路，而是時間。每個街廓都有自己的時間感，清代街區步調慢，日治區域相對整齊，戰後眷村則帶著濃厚的生活氣息。不要急著趕路，遇到有趣的建築或店家就停下來，跟老闆聊兩句，往往能聽到意外的故事。\n\n另外，避免在歷史街區追求速度感，這裡的價值在於細節觀察。建議帶一本臺北老地圖對照，會發現很多街道紋理的歷史邏輯。最重要的是保持好奇心，不要把這些地方當作拍照背景，而是試著理解每個角落背後的歷史意義。",
  "license": "CC BY 4.0"
}