{
  "title": "九份老街伴手禮推薦：買鳳梨酥前先搞懂的在地選擇",
  "slug": "taiwan-shopping-pineapple-cakes-jiufen-九份老街伴手禮推薦-買鳳梨酥前先搞懂的在地選擇-fa0699",
  "industry": "shopping",
  "category": "pineapple-cakes",
  "area": "jiufen",
  "url": "https://taiwan-encyclopedia.vercel.app/articles/taiwan-shopping-pineapple-cakes-jiufen-九份老街伴手禮推薦-買鳳梨酥前先搞懂的在地選擇-fa0699.html",
  "published": "2026-07-04",
  "quality_score": 7.5,
  "word_count": 1395,
  "tags": [
    "九份",
    "九份老街",
    "伴手禮",
    "芋圓",
    "草仔粿"
  ],
  "content": "來九份老街，會買到鳳梨酥嗎？這個問題其實沒有標準答案，卻藏著很多遊客不知道的選購眉角。\n\n九份是臺灣最經典的山城風景區，日治時代因金礦繁榮，曾有「小上海」之稱。如今的九份老街（以基山街、豎崎路為核心）仍是國內外觀光客必訪的景點，但這裡並非鳳梨酥的傳統產地。走在老街上，你會看到芋圓、草仔粿、傳統茶點等濃濃在地風情的點心，卻很少看到店家主打「九份在地製作鳳梨酥」。\n\n這其實不是壞事。許多標榜「九份鳳梨酥」的產品，其實來自鄰近的基隆、瑞芳，或是北部其他縣市的工廠製作，價格落在每盒 NT$150-300 元區間，和一般通路鳳梨酥大同小異。真正值得你在九份關注的，是以下這些更具地方特色的選擇：\n\n**推薦一：阿妹茶樓**\n位於豎崎路上的阿妹茶樓，可說是九份最富代表性的茶屋。雖然這裡不以鳳梨酥聞名，但茶樓自製的茶點組合非常適合送禮。店內備有烏龍茶點心禮盒，價格約 NT$200-400 元，包含茶香餅乾、傳統小點心，搭配精緻包裝，很能代表九份的茶文化底蘊。阿妹茶樓本身也是宮崎駿《神隱少女》湯婆婆湯屋的靈感來源之一，建築本身就是風景。\n\n**推薦二：阿柑姨芋圓**\n如果說九份有一款伴手禮非買不可，芋圓絕對榜上有名。阿柑姨是九份芋圓的老字號，位於基山街內的店面常常大排長龍。這裡的芋圓、地瓜圓、綠茶圓都是手工製作，冷熱皆宜。作為伴手禮，建議購買冷藏包裝的生芋圓（約 NT$80-120 元/包），回家自己煮更能品嚐 Q 彈口感。需要注意的是，芋圓保質期較短，適合當場食用或短程攜帶。\n\n**推薦三：九份金礦工藝**\n這家小店位於基山街尾端，專賣以九份金礦為主題的特色產品。店內有金箔點心、金箔巧克力等創意伴手禮，價格約 NT$150-300 元。雖然不是傳統鳳梨酥，但極具九份在地特色，送禮自用兩相宜。\n\n**推薦四：草仔粿專賣店**\n九份老街上至少有兩三家草仔粿攤位，這是傳統客家米食，內餡以蘿蔔絲、鹹菜為主，口感軟糯帶有艾草清香。一個約 NT$15-25 元，是很有古早味的隨手小點心。建議買盒裝的（一盒 6 入約 NT$100-150 元），當作伴手禮分送親友，既特別又不貴。\n\n**推薦五：昇平戲院前廣場周邊攤位**\n昇平戲院是九份最老的戲院，廣場周圍聚集了多家賣傳統零食的小攤。這裡可以找到古早味的蜜餞、烘焙堅果、花生糖等，價格實惠（NT$50-150 元就有交易），很適合買來辦公室分食。\n\n**實用資訊：**\n- 交通：從臺北車站搭乘臺鐵至瑞芳站，轉乘公車 788、825 或計程車前往九份老街；也可從捷運忠孝新生站搭乘公車 1062。開車建議停放在九份第二停車場（收費）。\n- 營業時間：老街店家大致從上午 10 點營業至傍晚 6-7 點，茶樓可能延長至晚上 8-9 點。\n- 費用：門票免費，停車場平日每小時 NT$30、假日 NT$50。\n- 最佳季節：九份四季皆宜，但冬季容易有雨，夏季悶熱。建議避開連續假日的人潮。\n\n**旅遊小提示：**\n來九份真的不用執著於買鳳梨酥。這裡的價值在於山城風情、百年老街和傳統茶文化。與其買一款來歷不明的「九份鳳梨酥」，不如選擇芋圓、草仔粿或茶點，不僅更有地方特色，價格也更實在。如果你真心想買鳳梨酥當伴手禮，建議從九份離開後，前往附近的基隆或瑞芳火車站，那裡有更多當地製作的選擇，或者直接前往臺中、雲林等傳統產地選購品質更穩定的產品。",
  "license": "CC BY 4.0"
}