{
  "title": "高雄夜間景點完全指南：愛河、西子灣與駁二的夜生活美學",
  "slug": "taiwan-entertainment-lantern-festival-kaohsiung-高雄夜間景點完全指南-愛河-西子灣與駁二的夜生活美學-21847b",
  "industry": "entertainment",
  "category": "lantern-festival",
  "area": "kaohsiung",
  "url": "https://taiwan-encyclopedia.vercel.app/articles/taiwan-entertainment-lantern-festival-kaohsiung-高雄夜間景點完全指南-愛河-西子灣與駁二的夜生活美學-21847b.html",
  "published": "2026-06-10",
  "quality_score": 6.5,
  "word_count": 1254,
  "tags": [
    "高雄夜景",
    "愛河",
    "西子灣",
    "駁二藝術特區",
    "高雄夜市"
  ],
  "content": "說到高雄的夜晚，很多人第一個想到的是元宵節的燈會，但老實說，高雄並沒有一個像臺北或臺南那樣明確命名的「高雄燈節」大型傳統活動。這點需要先說清楚，以免讀者抱著錯誤期待前來。\n\n不過，高雄的夜間魅力其實不在傳統燈會，而是這座城市獨有的港都夜色——從愛河的浪漫遊船到西子灣的夕陽，從駁二藝術特區的夜間展演到苓雅區的設計咖啡廳，高雄的夜晚有著不同於其他城市的悠閒與開闊。\n\n愛河可以說是高雄夜間的代表景點。這條流經市區的河流，晚間會有遊船服務，沿途可以欣賞河岸的夜景與裝置藝術。遊船價格大約在新臺幣200至300元之間，航程約30分鐘，適合情侶或想要放鬆的旅人。愛河沿岸也有不少咖啡廳和餐廳，夜晚坐著喝杯飲料吹吹河風，是高雄人日常的休閒方式。值得一提的是，愛河在某些節日會有水上燈光秀或投影表演，這時候的氣氛特別熱鬧，但這些活動通常不是固定舉辦的「燈節」，而是節慶期間的特別企劃。\n\n西子灣是另一個推薦的夜間去處。這裡以夕陽聞名，但傍晚時分的景色同樣動人。看著太陽從海平面落下，港都的輪廓漸漸浮現在暮色中，是一種不同於都會夜景的開闊感。西子灣捷運站附近有許多小吃攤販，看完夕陽順便吃個晚餐，是很典型的在地玩法。從西子灣可以搭船前往旗津，旗津的夜晚也很熱鬧，海產店的露天座位在夜色中特別有氣氛。\n\n駁二藝術特區是近年高雄最受到年輕人喜愛的夜間景點之一。這裡原本是廢棄的港口倉庫，經過活化後成為藝術特區，常有各種展覽和市集。晚上的駁二很有氣氛，倉庫外牆的塗鴉和燈光搭配得很適合拍照。特區內有幾家咖啡廳和文創商店，營業時間通常到晚上九點左右。對於喜歡藝術和文創的人來說，駁二是高雄夜晚的首選。\n\n如果想要體驗高雄的夜市文化，六合夜市和瑞豐夜市是兩個主要選擇。六合夜市靠近美麗島捷運站，是歷史悠久的夜市，以小吃聞名。瑞豐夜市在左營區，每週二、五、六、日營業，攤位比六合多，也比較熱鬧。這兩個夜市的消費方式很親民，一攤吃一點可以吃得很滿足。\n\n對於喜歡唱歌的人來說，高雄的KTV也有自己的特色。由於是港口城市，一些KTV有海景包廂，唱歌的同時可以看到港區夜景，價格會比一般包廂貴一些。學生或小資族可以選擇離峰時段，通常會有折扣優惠。\n\n交通方面，高雄捷運是最方便的選擇。紅線和橘線串聯了主要景點，愛河在橘線市議會站附近，六合夜市在美麗島站，駁二在橘線鹽埕埔站，西子灣則需要轉乘渡輪。高雄的公車班次相對捷運較少，但主要景點都可以透過捷運到達。\n\n說實在的，高雄沒有傳統意義上的大型燈節，這點與其城市特性有關——高雄的夜間魅力在於悠閒的港都氣氛和多元的藝術空間，而非節慶式的燈會活動。如果想要體驗傳統燈節，臺南的鹽水蜂炮或臺北的燈會可能更符合期待。但如果你想感受不一樣的夜生活，高雄的愛河、駁二和夜市絕對值得一訪。\n\n最佳造訪季節是高雄的冬季到春季（11月至3月），天氣涼爽適合戶外活動。夏季雖然天氣炎熱，但可以利用傍晚的時間，先去西子灣看夕陽，再進市區逛夜市。高雄的夜生活營業時間通常到凌晨12點左右，夜市則依攤位不同而有差異。",
  "license": "CC BY 4.0"
}