{
  "title": "日月潭購物攻略：湖畔特色小店與伴手禮精選",
  "slug": "taiwan-shopping-department-stores-sun-moon-lake-日月潭購物攻略-湖畔特色小店與伴手禮精選-7de30c",
  "industry": "shopping",
  "category": "department-stores",
  "area": "sun-moon-lake",
  "url": "https://taiwan-encyclopedia.vercel.app/articles/taiwan-shopping-department-stores-sun-moon-lake-日月潭購物攻略-湖畔特色小店與伴手禮精選-7de30c.html",
  "published": "2026-07-13",
  "quality_score": 7.5,
  "word_count": 1941,
  "tags": [
    "日月潭購物",
    "南投伴手禮",
    "日月潭茶葉",
    "水里陶藝",
    "日月潭文創"
  ],
  "content": "說起日月潭的購物體驗，許多初次造訪的遊客會期待找到大型百貨公司，但走進潭區後會發現，這裡的購物場域以另一種姿態呈現——沒有氣派的天井與電扶梯，卻有著更貼近土地的溫度。這篇文章不談連鎖百貨，而是帶你走進日月潭周邊那些值得駐足的小店，從茶葉到手工藝，從晨間到傍晚，用不同的時間維度體會湖畔的購物日常。\n\n## 特色亮點：沒有百貨的獨特購物哲學\n\n日月潭的零售場域以「精而不雜」取勝。相較於都會區的複合式商場，這裡的店家往往專精單一領域，且與當地產業深度連結。來到日月潭，不能錯過的是臺茶十八號（紅玉）的故鄉風情——魚池鄉的茶葉品質聞名全臺，許多茶行更是自產自銷，從茶園到店面只有幾步路的距離。此外，潭區的手工藝品店也頗具特色，許多店主是移居至此的藝術工作者，他們將日月潭的山水意象融入作品，形成獨一無二的文創商品。值得注意的是，近年來咖啡文化興起，魚池鄉的咖啡種植面積逐年增加，街頭巷尾的咖啡小店也成為購物之餘的新選擇。\n\n## 推薦地點\n\n**一、喝喝茶。日月潭紅玉茶葉專門店**\n這間位於魚池市區的茶葉專賣店，距離日月潭潭邊約十五分鐘車程，卻是許多老饕指定的茶葉採購點。店家主打臺茶十八號（紅玉）與臺茶二十一號（紅韻），前者帶有薄荷與肉桂的獨特香氣，後者則以花果甜香著稱。店內提供免費茶飲試喝，服務人員會根據你的口味偏好推薦適合的茶款。價格方面，茶葉禮盒組約 NT$800 至 NT$3,000 不等，單品茶葉每臺斤（600g）從 NT$400 起跳。這裡的茶葉品質穩定，送禮自用兩相宜，是日月潭最具代表性的伴手禮選擇之一。\n\n**二、暨大師生創意市集（週六限定）**\n如果你在週六造訪日月潭，千萬別錯過位於水里鄉的暨南國際大學週六市集。這個由大學師生發起的創意市集，聚集了手作飾品、手工皂、二手書籍與在地農產品。每個攤位都有自己的故事——有學生以日月潭風景創作的明信片，也有老師傅傳承的草編藝術品。價格相對親民，大部分商品落在 NT$100 至 NT$800 之間，是尋找獨特紀念品的好去處。市集時間為每週六上午九點至下午兩點，規模不大但質精值得細逛。\n\n**三、 日月潭湖畔手感生活**\n這間位於伊達邵碼頭附近的手作選物店，店內集結了來自臺灣各地設計師的作品，從陶藝到皮革製品都有。店主特別強調「可持續生活」的理念，許多商品以環保素材製作。最受歡迎的是以日月潭風景為靈感的陶瓷杯墊，每組 NT$350，圖案細膩且實用。此外，店內也有販售來自南投山區的天然蜂蜜與梅精，價格實惠。這裡適合想買有質感又不過度商業化禮物的旅客。\n\n**四、 宏基蜜蜂生態農場**\n距離日月潭約二十分鐘車程的宏基蜜蜂農場，是體驗式購物的絕佳選擇。這裡不僅可以參觀蜜蜂生態、瞭解蜂蜜產生過程，還能直接購買各式蜂蜜產品。農場的招牌商品包括龍眼蜜（NT$380/罐）、荔枝蜜（NT$350/罐）以及蜂王乳膠囊（NT$1,200/盒）。農場附設的咖啡廳供應蜂蜜拿鐵與花粉餅，逛累了可以坐下休息品嚐。這個景點結合了教育與購物，非常適合親子同遊。\n\n**五、 水裡蛇窯陶藝文化館**\n水里鄉是臺灣傳統陶藝的重鎮，這間已有六十多年歷史的蛇窯轉型而成的文化館，展示了老窯廠的風貌，並販售手工製作的陶藝品。與一般紀念品店不同，這裡的每一件作品都有手工的溫度，從實用的茶具到裝飾性的陶偶都有。價格範圍很廣，茶具組從 NT$600 起，名家作品則可能達到 NT$10,000 以上。如果你想找一件真正有故事的手工藝品，這裡不會讓你失望。\n\n## 實用資訊\n\n**交通建議**：自行開車是最便利的選擇，日月潭周邊停車場收費約 NT$50-100/小時。若搭乘大眾運輸，可從臺中火車站轉乘南投客運（臺灣好行），票價約 NT$120-150。\n\n**營業時間**：大部分店家上午十點開門，下午五點至六點關門。茶葉店與特產店週一到週日都有營業，創意市集僅限週六。\n\n**價格參考**：日月潭周邊的伴手禮價格適中，茶葉禮盒 NT$800-3,000、手工藝品 NT$300-2,000、蜂蜜 NT$300-500。建議避開伊達邵碼頭的主街道，那裡的紀念品價格偏高且同質性高。\n\n## 旅遊小提示\n\n購物時間的選擇會大大影響體驗。清晨造訪茶葉店，往往能避開人潮，獲得更完整的解說服務。傍晚時分去湖畔的手感小店，有機會遇到店主閒聊，聽到更多關於商品背後的故事。此外，別忘了善用「滿額免稅」的服務——部分茶葉店消費滿 NT$3,000 可辨理退稅。對於開車族建議將車停在水里鄉的公有停車場，收費比潭區優惠許多，一天只需 NT$100 有找。日月潭的購物體驗不在於大型商場的便利，而在於小店積累的人情味與在地好物，這才是潭區最珍貴的伴手禮風景。",
  "license": "CC BY 4.0"
}