{
  "title": "臺中珍珠奶茶：從發源地到創新重鎮的茶飲脈絡",
  "slug": "taiwan-dining-bubble-tea-taichung-臺中珍珠奶茶-從發源地到創新重鎮的茶飲脈絡-a1d5bc",
  "industry": "dining",
  "category": "bubble-tea",
  "area": "taichung",
  "url": "https://taiwan-encyclopedia.vercel.app/articles/taiwan-dining-bubble-tea-taichung-臺中珍珠奶茶-從發源地到創新重鎮的茶飲脈絡-a1d5bc.html",
  "published": "2026-06-25",
  "quality_score": 7.5,
  "word_count": 1008,
  "tags": [
    "臺中珍珠奶茶",
    "春水堂",
    "台中美食",
    "珍珠奶茶發源地",
    "草悟道"
  ],
  "content": "說到珍珠奶茶的故鄉，臺中絕對是無法繞過的核心城市。1980年代中期，臺中春水堂前身「陽羨茶行」研發出第一杯以粉圓加茶的現代珍珠奶茶，從此改變了全球飲料市場的格局。這裡不僅是珍珠奶茶的誕生地，更是持續引領風潮的創新重鎮。\n\n臺中珍珠奶茶最大的特色在於「茶味偏重」這四個字。與北部偏甜、西部偏淡的口感不同，臺中在地茶飲向來重視茶葉本身的甘醇度，奶精或牛奶的比例相對較低，呈現出的是一種茶香與奶香平衡卻又以茶為主角的獨特風味。這樣的飲食習慣也直接影響了配料選擇——臺中的珍珠普遍煮得較Q彈，因為茶味重的基底需要口感更扎實的配料來達成整體平衡。\n\n若以店家風格型別來區分，臺中珍珠奶茶店大致可分為三種主要取向：\n\n**傳承經典派**：以春水堂為代表，堅持傳統茶葉現萃的工藝，選單品項相對精簡，但每一款都是經典。這類店家通常設有內用座位區，空間設計偏中式古典風格，適合想要體驗珍珠奶茶起源文化的消費者。\n\n**文青質感派**：集中在審計新村、範特喜綠光計劃等文創聚落周邊，外觀裝潢走低調簡約風，選單常加入燕麥奶、椰奶等植物奶選項。這類店家的客群以年輕女性和文青族群為主，價格帶約在NT$70-120之間，適合重視氛圍勝於口感的客人。\n\n**創新實驗派**：隱藏在巷弄中的小型茶飲工作室，經常推出限定口味或特色配料，例如木耳珍珠、桂花凍、寒天晶球等。這類店家資訊較不透明，多透過社群媒體發布新產品，是內行人才知的口袋名單。\n\n**實用資訊**\n\n前往臺中品嚐珍珠奶茶，交通相當便利。若從臺中火車站出發，可搭乘公車至英才路、大墩路一帶，這裡是傳統茶飲店的集結地；若想走文青路線，審計新村位於草悟道附近，步行即可抵達多家質感茶飲店。臺中市區公車基本收費為NT$22-28，使用悠遊卡可享轉乘優惠。\n\n價格方面，臺中珍珠奶茶的均價約在NT$55-100之間，傳統茶飲店的經典款通常落在NT$55-70區間，文青質感派的特調飲品則可能達到NT$120以上。建議避開下午2-4點的離峰時段，此時人潮較少，較能慢慢挑選。\n\n**旅遊小提示**\n\n想要深入體驗臺中珍珠奶茶文化，建議安排半天的「茶飲巡禮」：上午先參觀春水堂的創始店，品嚐最原汁原味的經典款；中午在草悟道周邊的文創小店休息，順便嘗試當季限定；傍晚則可前往巷弄中的隱藏版茶飲工作室，感受臺中人的創意能量。記得攜帶環保杯，部分店家提供自備杯優惠NT$5，這可是內行人的才知道的眉角。",
  "license": "CC BY 4.0"
}