{
  "title": "花蓮Live House不完全指南：山谷間的音樂現場",
  "slug": "taiwan-entertainment-live-houses-hualien-花蓮live-house不完全指南-山谷間的音樂現場-0abb51",
  "industry": "entertainment",
  "category": "live-houses",
  "area": "hualien",
  "url": "https://taiwan-encyclopedia.vercel.app/articles/taiwan-entertainment-live-houses-hualien-花蓮live-house不完全指南-山谷間的音樂現場-0abb51.html",
  "published": "2026-05-25",
  "quality_score": 6.5,
  "word_count": 1578,
  "tags": [
    "花蓮",
    "Live House",
    "音樂現場",
    "台灣音樂",
    "花蓮旅遊"
  ],
  "content": "說來可能讓許多人意外——花蓮其實並沒有典型意義上的Live House。這座被中央山脈環抱的縣市，因地形因素長期缺乏都會型的現場音樂展演空間。相較於臺北、桃園的成熟的Live House產業聚落，花蓮的音樂場景走的是一條完全不同的路線。\n\n然而，正是這種「沒有」的特質，反而催生出花蓮獨有的音樂體驗形態。如果你期待的是東京澀谷或臺北華山那種規格化的Live House，可能會失望；但如果你願意敞開心胸接受不一樣的可能性，花蓮能提供一種更原始、更在地、更有機的音樂接近方式。\n\n### 花蓮音樂場景的核心特色\n\n花蓮的音樂現場有別於西部的幾個鮮明特徵：首先，演出場所極度分散，沒有集中的「音楽園區」概念；其次，許多表演發生在非正規場合——咖啡廳、民宿、工坊、甚至海邊或部落廣場；第三，業者往往身兼多職，可能是老闆也是演出者，這種「垂直整合」形態反而讓票價更具彈性，歌手與觀眾的距離也更加接近。\n\n近年來隨著臺9線公路改善與腳踏車活動興起，花蓮的文創產業正在緩慢發展，部分新的複合式空間開始引進現場音樂活動，這個趨勢值得持續關注。\n\n### 實際可走訪的音樂相關場所\n\n**鐵花好日**\n位於花蓮市區的鐵花路上，是少數以「音樂」為主題的複合式空間。這個據點結合了咖啡輕食與不定期的現場演出，雖然規模不大，但常有本地創作歌手駐唱。空間採用預約制，演出資訊通常公佈在店家的社群帳號上。票價落在200-300元之間（含一杯飲料）。營業時間主要為晚上七點到十一點，週末較有機會遇到現場演出。\n\n**Home work咖啡**\n這間位於市中心的老牌咖啡館，長期支援本地音樂人，曾舉辦過多場不插電形式的迷你演唱會。空間不大，只有二十來個座位，但氣氛溫馨，歌手與觀眾幾乎零距離。由於不是專業Live House，演出資訊較不固定，往往需要直接在現場詢問或在臉書追蹤粉絲專頁。\n\n**部落音樂場**\n花蓮擁有豐富的原住民文化資源，瑞穗、太魯閣、馬遠等部落的社群活動中心偶爾會舉辦傳統歌謠或現代創作的表演。這類活動通常免費或隨喜捐獻，是理解花蓮音樂文化根源的絕佳途徑。若有幸遇到千萬不要錯過，這是只有在花蓮才有的獨特體驗。\n\n**海岸線的即興音樂**\n七星潭與石門沿海一帶，天氣允許的夏夜，常有街頭藝人或獨立音樂人自發性地彈吉他唱歌。這類沒有舞臺的「野生Live House」雖然不穩定，卻充滿驚喜。建議在黃昏時分前往，運氣好的話能遇到很棒的音樂風景。\n\n\n### 實用資訊\n\n關於費用方面，花蓮music related活動的票價普遍比西部便宜，不插電的小型演出通常免費或低於200元；即便是較正式的售票演出，票價也很少超過500元，這是偏鄉消費的優勢。\n\n交通方式建議以租借機車最為便利，公亦有但班次有限。自臺北方向前來可搭乘臺鐵至花蓮站，區間車約需兩小時。開車的話經蘇花改公路從臺北出發約三至三點五小時抵達。\n\n最佳體驗時間落在每年四月到六月與九月至十一月，天氣穩定且較少颱風干擾。夏季雖偶有演出，但雨季與颱風季節會影響活動的穩定性。週末的演出機會通常比周間更多。\n\n### 旅遊小提示\n\n切記一點：來花蓮尋找Live House的心態要正確——這裡沒有「朝聖」性質的大型音樂場館，但如果願意走低調探索路線，收獲可能超出預期。建議出發前先在網路上搜尋最新的活動訊息，因為情報更新速度很快，現場詢問往往比網路更準確。\n\n另一個秘訣是：如果在正規場所找不到演出資訊，不妨直接走進街角的咖啡館或小型酒吧詢問。老闆很可能就是幕後推手，這種人情味式的資訊管道，正是花蓮音樂場景最大的魅力所在。\n\n最後，如果純粹為了Live House而專程前往花蓮，可能會有失落感；但如果計畫結合太魯閣 Marathon、生態導覽或部落文化體驗，同時將音樂元素當作加分亮點，那麼花蓮絕對值得一訪。",
  "license": "CC BY 4.0"
}