{
  "title": "日月潭溫泉文化散策：從邵族部落到日式湯治的在地故事",
  "slug": "taiwan-tourism-hot-springs-sun-moon-lake-日月潭溫泉文化散策-從邵族部落到日式湯治的在地故事-094c6e",
  "industry": "tourism",
  "category": "hot-springs",
  "area": "sun-moon-lake",
  "url": "https://taiwan-encyclopedia.vercel.app/articles/taiwan-tourism-hot-springs-sun-moon-lake-日月潭溫泉文化散策-從邵族部落到日式湯治的在地故事-094c6e.html",
  "published": "2026-03-29",
  "quality_score": 6.5,
  "word_count": 1436,
  "tags": [
    "日月潭溫泉",
    "邵族文化",
    "湯治文化",
    "溫泉飯店",
    "部落體驗"
  ],
  "content": "作為一個走遍臺灣老街的文史工作者，我必須先誠實告訴你：日月潭並非傳統意義上的溫泉勝地。這裡的溫泉資源確實有限，遠不如關子嶺或烏來來得豐富。但正因如此，這裡的溫泉體驗帶有一種獨特的文化層次，值得細細品味。\n\n## 被忽視的溫泉文化脈絡\n\n日月潭的溫泉發展，其實承載著臺灣近代史的縮影。日治時期，日本人在此地推廣「湯治文化」，企圖將內地的溫泉療養概念移植到臺灣。但與陽明山或北投的大規模開發不同，日月潭的溫泉始終保持著相對樸素的面貌，這反而讓它在今日過度商業化的溫泉市場中，顯得格外珍貴。\n\n邵族人稱溫泉為「malastapang」，意指「會冒煙的水」。對部落而言，這些地熱不僅是自然資源，更是祖靈居住的神聖場所。這樣的文化背景，讓日月潭的溫泉體驗多了一層靈性色彩，區別於純粹的商業消費。\n\n## 精選溫泉體驗地點\n\n**涵碧樓溫泉**\n地址：南投縣魚池鄉中興路142號\n這裡是日月潭唯一能稱得上頂級的溫泉設施。NT$8000-12000的房價確實不親民，但半開放式的湯屋設計，讓你能在泡湯時直視湖面，那種體驗確實無可取代。重點是它的碳酸氫納泉質溫和，適合長時間浸泡。\n\n**雲品酒店日式風呂**\n地址：南投縣魚池鄉日月村中正路23號\n相較涵碧樓的奢華，雲品的定位更務實。NT$4500-6500的價格帶來相當不錯的CP值。它的露天風呂採用檜木建造，那種木頭香氣混合著湖水氣息的感覺，很有日式湯屋的韻味。\n\n**馥麗溫泉大飯店**\n地址：南投縣魚池鄉日月村水社路142號\n這是日月潭最平價的溫泉選擇，NT$2800-3500就能享受基本的溫泉設施。雖然景觀不如前兩家，但對於想要體驗日月潭溫泉又不想花大錢的遊客來說，算是實在的選擇。\n\n**日月行館溫泉SPA**\n地址：南投縣魚池鄉日月村中興路139號\n這裡主打的是SPA結合溫泉的概念，NT$1200的日歸溫泉相當實惠。雖然設施稍顯老舊，但勝在價格親民，而且從這裡能看到完整的日月潭全景。\n\n**伊達邵部落溫泉**\n地址：南投縣魚池鄉日月村德化街6號\n這是最具文化意義的選擇。由邵族文化發展協會經營，NT$300的泡腳池雖然簡單，但你能在這裡聽到部落長者講述溫泉的古老傳說。建議搭配部落美食體驗，更能感受在地文化。\n\n## 實用資訊整理\n\n**交通方式**\n從臺北出發：搭乘國光客運1833路線至日月潭，車程約3.5小時，票價NT$460。自駕走國道6號至魚池交流道，約3小時車程。\n\n**最佳造訪時間**\n11月至3月是溫泉旺季，房價會上漲30-50%。我個人推薦4-5月的春季，氣溫適中且遊客較少，更能享受寧靜的泡湯體驗。\n\n**費用參考**\n- 高階溫泉飯店：NT$8000-12000/晚\n- 中階溫泉住宿：NT$3500-6500/晚\n- 日歸溫泉：NT$300-1200/次\n- 部落文化體驗：NT$300-500/人\n\n## 老街人的誠實建議\n\n日月潭的溫泉確實無法與北投、烏來等地相提並論，泉質和設施都相對普通。但如果你把它當作湖光山色中的文化體驗，而非純粹的溫泉之旅，就會發現它的價值所在。\n\n特別建議安排兩天一夜的行程，第一天體驗部落文化和平價溫泉，第二天再享受高階飯店的奢華設施。這樣的安排既能深度體驗在地文化，又能滿足舒適度需求。\n\n避開假日和陸客團密集的時段，選擇平日造訪，你會發現一個更加寧靜、更具靈性的日月潭溫泉世界。記住，這裡的溫泉不是為了炫耀消費，而是為了讓身心在湖光山色中得到真正的沉澱。",
  "license": "CC BY 4.0"
}